Workbook

Sheet Read me
A1: Nkambe recipe and costing registers H3
A2: 8 October 2026 — all formulas require production validation
A3: Prices holds editable FCFA/kg. Empty cells mean unknown, not zero.
A4: Ingredients recalculates direct prices and prepared-component subtotals. Component rates use the usable mass on Summary; update that mass after measured yield changes.
A5: Summary shows known ingredient subtotals only; full variable cost and selling price must be entered separately before contribution is computed.
A6: Missing-price counts cover direct lines; review each prepared-component recipe too. Original missing-input notes are the export snapshot.
A7: Oil price/kg uses provisional 0.92 kg/L. Do not apply Top Milk to unspecified condensed milk.
A8: Source IDs and exact cell references are preserved in the comparison and source sheets.
A9: BAG-H2-01 uses a 40-piece pilot and 80-piece load. Its checked H2 model is carried unchanged in the H3 planner.
A10: H3: EDC is separate and unpriced. T01 and H05 are held, with usable yield and unit-cost calculation withdrawn. See EDC correction.

Sheet Prices
A1: Ingredient | B1: FCFA per kg editable | C1: Basis / specification
A2: Bread flour | B2: 420 | C2: Owner flour price; flour performance requires trial
A3: Water | C3: Purchase quote/specification required
A4: Sugar | B4: 640 | C4: Owner granulated sugar price; grind specification must match
A5: Margarine | B5: 1333.3333 | C5: Roma; fat, salt and application suitability unconfirmed
A6: Salt | B6: 194.44444 | C6: Owner price
A7: Yeast | B7: 1666.6667 | C7: Nevada instant dry; sweet-dough suitability requires trial
A8: Condensed milk | C8: Purchase quote/specification required
A9: Egg | C9: Purchase quote/specification required
A10: Whole milk powder | C10: Purchase quote/specification required
A11: Vanilla | C11: Purchase quote/specification required
A12: Sweet potato flour | C12: Purchase quote/specification required
A13: Nutmeg | C13: Purchase quote/specification required
A14: Plain flour | C14: Purchase quote/specification required
A15: Baking powder | C15: Purchase quote/specification required
A16: Canned fish drained | C16: Purchase quote/specification required
A17: Onion trimmed | C17: Purchase quote/specification required
A18: Carrot trimmed | C18: Purchase quote/specification required
A19: Oil | B19: 1413.0435 | C19: PROVISIONAL 0.92 kg/L; correct after weighing
A20: Garlic peeled | C20: Purchase quote/specification required
A21: Ginger peeled | C21: Purchase quote/specification required
A22: Black pepper | C22: Purchase quote/specification required
A23: Paprika | C23: Purchase quote/specification required
A24: Beef mince | C24: Purchase quote/specification required
A25: Potato peeled | C25: Purchase quote/specification required
A26: Thyme | C26: Purchase quote/specification required
A27: Curry powder | C27: Purchase quote/specification required
A28: Sausage meat | C28: Purchase quote/specification required
A29: Breadcrumbs | C29: Purchase quote/specification required
A30: Chicken boneless | C30: Purchase quote/specification required
A31: Pepper trimmed | C31: Purchase quote/specification required
... A71: Peanut roasted | C71: Purchase quote/specification required
A72: Nevada instant dry yeast | B72: 1666.6667 | C72: Nevada instant dry; sweet-dough suitability requires trial
A73: Margarine 80% | C73: Purchase quote/specification required
A74: Butter 82% | C74: Purchase quote/specification required
A75: Whole egg | C75: Purchase quote/specification required
A76: Whole milk 3.5% | C76: Purchase quote/specification required
A77: Desiccated coconut | C77: Purchase quote/specification required
A78: Banana pulp | C78: Purchase quote/specification required
A79: Raw beef mince | C79: Purchase quote/specification required
A80: Pasteurized-egg mayonnaise | C80: Purchase quote/specification required
A81: Drained pickle | C81: Purchase quote/specification required
A82: Drained sardines | C82: Purchase quote/specification required
A83: Carrot | C83: Purchase quote/specification required
A84: Tomato paste | C84: Purchase quote/specification required
... A105: Pasteurized mango puree 15 Brix | C105: Purchase quote/specification required
A106: Le Choix du Boulanger flour | B106: 420 | C106: Owner flour price; flour performance requires trial
A107: Potable water | C107: Purchase quote/specification required
A108: White granulated sugar | B108: 640 | C108: Owner granulated sugar price; grind specification must match
A109: Millac Premium powder | B109: 3200 | C109: Millac fat-filled powder trial; not skim or whole milk powder
A110: Roma margarine | B110: 1333.3333 | C110: Roma; fat, salt and application suitability unconfirmed
A111: Fine food-grade salt | B111: 194.44444 | C111: Owner price
A112: Unsweetened fine desiccated coconut | C112: Purchase quote/specification required
A113: Ready-to-use seedless raisins | C113: Purchase quote/specification required
A114: Ground cinnamon | C114: Purchase quote/specification required
A115: Neutral food-grade oil | B115: 1413.0435 | C115: PROVISIONAL 0.92 kg/L; correct after weighing
A116: Food-grade garlic powder | C116: Purchase quote/specification required
A117: Dried mixed herbs | C117: Purchase quote/specification required
A118: Baking powder double acting | C118: Purchase quote/specification required
A119: Egg edible mass | C119: Purchase quote/specification required
A120: Whole wheat flour | C120: Purchase quote/specification required
A121: Honey | C121: Purchase quote/specification required
A122: Vanilla extract | C122: Purchase quote/specification required
A123: Unsweetened cocoa | C123: Purchase quote/specification required
A124: Ground nutmeg | C124: Purchase quote/specification required
A125: Pasteurized whole milk | C125: Purchase quote/specification required
A126: Vanilla sugar | C126: Purchase quote/specification required
A127: Fresh lime zest | C127: Purchase quote/specification required
... A140: Ready-to-eat roasted groundnuts | C140: Purchase quote/specification required
A141: Top Milk concentrated milk | B141: 1000 | C141: Owner price; composition/type unresolved; not mapped to sweetened condensed milk
A142: H2 flour | B142: 420 | C142: Owner quote / water unresolved
A143: H2 potable water | C143: Owner quote / water unresolved
A144: H2 salt | B144: 194.44444 | C144: Owner quote / water unresolved
A145: H2 Nevada | B145: 1666.6667 | C145: Owner quote / water unresolved
A146: EDC unidentified HOLD | C146: Identity and purchase price unresolved; not margarine

Sheet Ingredients
A1: Recipe ID | B1: Recipe | C1: Component | D1: Ingredient | E1: Pilot grams | F1: Commercial grams | G1: FCFA per kg | H1: Known extended FCFA | I1: Status / price basis | J1: Component reference
A2: O-B01 | B2: Family bread dough | C2: Main formula | D2: Bread flour | E2: 1000 | F2: 5000 | G2: =IF(Prices!B2="","",Prices!B2) | H2: =IF(G2="","",E2/1000*G2) | I2: Owner flour price; flour performance requires trial
A3: O-B01 | B3: Family bread dough | C3: Main formula | D3: Water | E3: 600 | F3: 3000 | G3: =IF(Prices!B3="","",Prices!B3) | H3: =IF(G3="","",E3/1000*G3) | I3: Purchase quote/specification required
A4: O-B01 | B4: Family bread dough | C4: Main formula | D4: Sugar | E4: 50 | F4: 250 | G4: =IF(Prices!B4="","",Prices!B4) | H4: =IF(G4="","",E4/1000*G4) | I4: Owner granulated sugar price; grind specification must match
A5: O-B01 | B5: Family bread dough | C5: Main formula | D5: Margarine | E5: 35 | F5: 175 | G5: =IF(Prices!B5="","",Prices!B5) | H5: =IF(G5="","",E5/1000*G5) | I5: Roma; fat, salt and application suitability unconfirmed
A6: O-B01 | B6: Family bread dough | C6: Main formula | D6: Salt | E6: 18 | F6: 90 | G6: =IF(Prices!B6="","",Prices!B6) | H6: =IF(G6="","",E6/1000*G6) | I6: Owner price
A7: O-B01 | B7: Family bread dough | C7: Main formula | D7: Yeast | E7: 12 | F7: 60 | G7: =IF(Prices!B7="","",Prices!B7) | H7: =IF(G7="","",E7/1000*G7) | I7: Nevada instant dry; sweet-dough suitability requires trial
A8: O-B02 | B8: Condensed milk bun dough | C8: Main formula | D8: Bread flour | E8: 1000 | F8: 5000 | G8: =IF(Prices!B2="","",Prices!B2) | H8: =IF(G8="","",E8/1000*G8) | I8: Owner flour price; flour performance requires trial
A9: O-B02 | B9: Condensed milk bun dough | C9: Main formula | D9: Water | E9: 430 | F9: 2150 | G9: =IF(Prices!B3="","",Prices!B3) | H9: =IF(G9="","",E9/1000*G9) | I9: Purchase quote/specification required
A10: O-B02 | B10: Condensed milk bun dough | C10: Main formula | D10: Condensed milk | E10: 150 | F10: 750 | G10: =IF(Prices!B8="","",Prices!B8) | H10: =IF(G10="","",E10/1000*G10) | I10: Purchase quote/specification required
A11: O-B02 | B11: Condensed milk bun dough | C11: Main formula | D11: Sugar | E11: 80 | F11: 400 | G11: =IF(Prices!B4="","",Prices!B4) | H11: =IF(G11="","",E11/1000*G11) | I11: Owner granulated sugar price; grind specification must match
A12: O-B02 | B12: Condensed milk bun dough | C12: Main formula | D12: Egg | E12: 100 | F12: 500 | G12: =IF(Prices!B9="","",Prices!B9) | H12: =IF(G12="","",E12/1000*G12) | I12: Purchase quote/specification required
A13: O-B02 | B13: Condensed milk bun dough | C13: Main formula | D13: Margarine | E13: 80 | F13: 400 | G13: =IF(Prices!B5="","",Prices!B5) | H13: =IF(G13="","",E13/1000*G13) | I13: Roma; fat, salt and application suitability unconfirmed
A14: O-B02 | B14: Condensed milk bun dough | C14: Main formula | D14: Whole milk powder | E14: 20 | F14: 100 | G14: =IF(Prices!B10="","",Prices!B10) | H14: =IF(G14="","",E14/1000*G14) | I14: Purchase quote/specification required
A15: O-B02 | B15: Condensed milk bun dough | C15: Main formula | D15: Salt | E15: 16 | F15: 80 | G15: =IF(Prices!B6="","",Prices!B6) | H15: =IF(G15="","",E15/1000*G15) | I15: Owner price
A16: O-B02 | B16: Condensed milk bun dough | C16: Main formula | D16: Yeast | E16: 15 | F16: 75 | G16: =IF(Prices!B7="","",Prices!B7) | H16: =IF(G16="","",E16/1000*G16) | I16: Nevada instant dry; sweet-dough suitability requires trial
A17: O-B02 | B17: Condensed milk bun dough | C17: Main formula | D17: Vanilla | E17: 4 | F17: 20 | G17: =IF(Prices!B11="","",Prices!B11) | H17: =IF(G17="","",E17/1000*G17) | I17: Purchase quote/specification required
A18: O-B03 | B18: Sweet potato milk bread dough | C18: Main formula | D18: Bread flour | E18: 850 | F18: 4250 | G18: =IF(Prices!B2="","",Prices!B2) | H18: =IF(G18="","",E18/1000*G18) | I18: Owner flour price; flour performance requires trial
A19: O-B03 | B19: Sweet potato milk bread dough | C19: Main formula | D19: Sweet potato flour | E19: 150 | F19: 750 | G19: =IF(Prices!B12="","",Prices!B12) | H19: =IF(G19="","",E19/1000*G19) | I19: Purchase quote/specification required
A20: O-B03 | B20: Sweet potato milk bread dough | C20: Main formula | D20: Water | E20: 570 | F20: 2850 | G20: =IF(Prices!B3="","",Prices!B3) | H20: =IF(G20="","",E20/1000*G20) | I20: Purchase quote/specification required
A21: O-B03 | B21: Sweet potato milk bread dough | C21: Main formula | D21: Condensed milk | E21: 100 | F21: 500 | G21: =IF(Prices!B8="","",Prices!B8) | H21: =IF(G21="","",E21/1000*G21) | I21: Purchase quote/specification required
A22: O-B03 | B22: Sweet potato milk bread dough | C22: Main formula | D22: Sugar | E22: 40 | F22: 200 | G22: =IF(Prices!B4="","",Prices!B4) | H22: =IF(G22="","",E22/1000*G22) | I22: Owner granulated sugar price; grind specification must match
A23: O-B03 | B23: Sweet potato milk bread dough | C23: Main formula | D23: Margarine | E23: 50 | F23: 250 | G23: =IF(Prices!B5="","",Prices!B5) | H23: =IF(G23="","",E23/1000*G23) | I23: Roma; fat, salt and application suitability unconfirmed
A24: O-B03 | B24: Sweet potato milk bread dough | C24: Main formula | D24: Whole milk powder | E24: 20 | F24: 100 | G24: =IF(Prices!B10="","",Prices!B10) | H24: =IF(G24="","",E24/1000*G24) | I24: Purchase quote/specification required
A25: O-B03 | B25: Sweet potato milk bread dough | C25: Main formula | D25: Salt | E25: 18 | F25: 90 | G25: =IF(Prices!B6="","",Prices!B6) | H25: =IF(G25="","",E25/1000*G25) | I25: Owner price
A26: O-B03 | B26: Sweet potato milk bread dough | C26: Main formula | D26: Yeast | E26: 14 | F26: 70 | G26: =IF(Prices!B7="","",Prices!B7) | H26: =IF(G26="","",E26/1000*G26) | I26: Nevada instant dry; sweet-dough suitability requires trial
A27: O-B04 | B27: Yeast doughnut dough | C27: Main formula | D27: Bread flour | E27: 1000 | F27: 5000 | G27: =IF(Prices!B2="","",Prices!B2) | H27: =IF(G27="","",E27/1000*G27) | I27: Owner flour price; flour performance requires trial
A28: O-B04 | B28: Yeast doughnut dough | C28: Main formula | D28: Water | E28: 440 | F28: 2200 | G28: =IF(Prices!B3="","",Prices!B3) | H28: =IF(G28="","",E28/1000*G28) | I28: Purchase quote/specification required
A29: O-B04 | B29: Yeast doughnut dough | C29: Main formula | D29: Egg | E29: 100 | F29: 500 | G29: =IF(Prices!B9="","",Prices!B9) | H29: =IF(G29="","",E29/1000*G29) | I29: Purchase quote/specification required
A30: O-B04 | B30: Yeast doughnut dough | C30: Main formula | D30: Sugar | E30: 120 | F30: 600 | G30: =IF(Prices!B4="","",Prices!B4) | H30: =IF(G30="","",E30/1000*G30) | I30: Owner granulated sugar price; grind specification must match
A31: O-B04 | B31: Yeast doughnut dough | C31: Main formula | D31: Margarine | E31: 80 | F31: 400 | G31: =IF(Prices!B5="","",Prices!B5) | H31: =IF(G31="","",E31/1000*G31) | I31: Roma; fat, salt and application suitability unconfirmed
A32: O-B04 | B32: Yeast doughnut dough | C32: Main formula | D32: Whole milk powder | E32: 30 | F32: 150 | G32: =IF(Prices!B10="","",Prices!B10) | H32: =IF(G32="","",E32/1000*G32) | I32: Purchase quote/specification required
A33: O-B04 | B33: Yeast doughnut dough | C33: Main formula | D33: Salt | E33: 15 | F33: 75 | G33: =IF(Prices!B6="","",Prices!B6) | H33: =IF(G33="","",E33/1000*G33) | I33: Owner price
A34: O-B04 | B34: Yeast doughnut dough | C34: Main formula | D34: Yeast | E34: 18 | F34: 90 | G34: =IF(Prices!B7="","",Prices!B7) | H34: =IF(G34="","",E34/1000*G34) | I34: Nevada instant dry; sweet-dough suitability requires trial
A35: O-B04 | B35: Yeast doughnut dough | C35: Main formula | D35: Nutmeg | E35: 2 | F35: 10 | G35: =IF(Prices!B13="","",Prices!B13) | H35: =IF(G35="","",E35/1000*G35) | I35: Purchase quote/specification required
A36: O-B04 | B36: Yeast doughnut dough | C36: Main formula | D36: Vanilla | E36: 3 | F36: 15 | G36: =IF(Prices!B11="","",Prices!B11) | H36: =IF(G36="","",E36/1000*G36) | I36: Purchase quote/specification required
A37: O-B05 | B37: Puff puff batter | C37: Main formula | D37: Plain flour | E37: 1000 | F37: 5000 | G37: =IF(Prices!B14="","",Prices!B14) | H37: =IF(G37="","",E37/1000*G37) | I37: Purchase quote/specification required
A38: O-B05 | B38: Puff puff batter | C38: Main formula | D38: Water | E38: 700 | F38: 3500 | G38: =IF(Prices!B3="","",Prices!B3) | H38: =IF(G38="","",E38/1000*G38) | I38: Purchase quote/specification required
A39: O-B05 | B39: Puff puff batter | C39: Main formula | D39: Sugar | E39: 120 | F39: 600 | G39: =IF(Prices!B4="","",Prices!B4) | H39: =IF(G39="","",E39/1000*G39) | I39: Owner granulated sugar price; grind specification must match
A40: O-B05 | B40: Puff puff batter | C40: Main formula | D40: Salt | E40: 12 | F40: 60 | G40: =IF(Prices!B6="","",Prices!B6) | H40: =IF(G40="","",E40/1000*G40) | I40: Owner price
A41: O-B05 | B41: Puff puff batter | C41: Main formula | D41: Yeast | E41: 12 | F41: 60 | G41: =IF(Prices!B7="","",Prices!B7) | H41: =IF(G41="","",E41/1000*G41) | I41: Nevada instant dry; sweet-dough suitability requires trial
A42: O-B05 | B42: Puff puff batter | C42: Main formula | D42: Nutmeg | E42: 2 | F42: 10 | G42: =IF(Prices!B13="","",Prices!B13) | H42: =IF(G42="","",E42/1000*G42) | I42: Purchase quote/specification required
A43: O-B06 | B43: Fish roll dough | C43: Main formula | D43: Plain flour | E43: 1000 | F43: 5000 | G43: =IF(Prices!B14="","",Prices!B14) | H43: =IF(G43="","",E43/1000*G43) | I43: Purchase quote/specification required
A44: O-B06 | B44: Fish roll dough | C44: Main formula | D44: Water | E44: 470 | F44: 2350 | G44: =IF(Prices!B3="","",Prices!B3) | H44: =IF(G44="","",E44/1000*G44) | I44: Purchase quote/specification required
A45: O-B06 | B45: Fish roll dough | C45: Main formula | D45: Margarine | E45: 100 | F45: 500 | G45: =IF(Prices!B5="","",Prices!B5) | H45: =IF(G45="","",E45/1000*G45) | I45: Roma; fat, salt and application suitability unconfirmed
A46: O-B06 | B46: Fish roll dough | C46: Main formula | D46: Sugar | E46: 60 | F46: 300 | G46: =IF(Prices!B4="","",Prices!B4) | H46: =IF(G46="","",E46/1000*G46) | I46: Owner granulated sugar price; grind specification must match
A47: O-B06 | B47: Fish roll dough | C47: Main formula | D47: Whole milk powder | E47: 20 | F47: 100 | G47: =IF(Prices!B10="","",Prices!B10) | H47: =IF(G47="","",E47/1000*G47) | I47: Purchase quote/specification required
A48: O-B06 | B48: Fish roll dough | C48: Main formula | D48: Salt | E48: 15 | F48: 75 | G48: =IF(Prices!B6="","",Prices!B6) | H48: =IF(G48="","",E48/1000*G48) | I48: Owner price
A49: O-B06 | B49: Fish roll dough | C49: Main formula | D49: Yeast | E49: 12 | F49: 60 | G49: =IF(Prices!B7="","",Prices!B7) | H49: =IF(G49="","",E49/1000*G49) | I49: Nevada instant dry; sweet-dough suitability requires trial
A50: O-B06 | B50: Fish roll dough | C50: Main formula | D50: Nutmeg | E50: 2 | F50: 10 | G50: =IF(Prices!B13="","",Prices!B13) | H50: =IF(G50="","",E50/1000*G50) | I50: Purchase quote/specification required
A51: O-B07 | B51: Shortcrust pie pastry | C51: Main formula | D51: Plain flour | E51: 1000 | F51: 5000 | G51: =IF(Prices!B14="","",Prices!B14) | H51: =IF(G51="","",E51/1000*G51) | I51: Purchase quote/specification required
A52: O-B07 | B52: Shortcrust pie pastry | C52: Main formula | D52: Margarine | E52: 400 | F52: 2000 | G52: =IF(Prices!B5="","",Prices!B5) | H52: =IF(G52="","",E52/1000*G52) | I52: Roma; fat, salt and application suitability unconfirmed
A53: O-B07 | B53: Shortcrust pie pastry | C53: Main formula | D53: Water | E53: 290 | F53: 1450 | G53: =IF(Prices!B3="","",Prices!B3) | H53: =IF(G53="","",E53/1000*G53) | I53: Purchase quote/specification required
A54: O-B07 | B54: Shortcrust pie pastry | C54: Main formula | D54: Egg | E54: 60 | F54: 300 | G54: =IF(Prices!B9="","",Prices!B9) | H54: =IF(G54="","",E54/1000*G54) | I54: Purchase quote/specification required
A55: O-B07 | B55: Shortcrust pie pastry | C55: Main formula | D55: Salt | E55: 15 | F55: 75 | G55: =IF(Prices!B6="","",Prices!B6) | H55: =IF(G55="","",E55/1000*G55) | I55: Owner price
A56: O-B07 | B56: Shortcrust pie pastry | C56: Main formula | D56: Baking powder | E56: 8 | F56: 40 | G56: =IF(Prices!B15="","",Prices!B15) | H56: =IF(G56="","",E56/1000*G56) | I56: Purchase quote/specification required
A57: O-B08 | B57: Fish filling | C57: Main formula | D57: Canned fish drained | E57: 500 | F57: 2500 | G57: =IF(Prices!B16="","",Prices!B16) | H57: =IF(G57="","",E57/1000*G57) | I57: Purchase quote/specification required
A58: O-B08 | B58: Fish filling | C58: Main formula | D58: Onion trimmed | E58: 150 | F58: 750 | G58: =IF(Prices!B17="","",Prices!B17) | H58: =IF(G58="","",E58/1000*G58) | I58: Purchase quote/specification required
A59: O-B08 | B59: Fish filling | C59: Main formula | D59: Carrot trimmed | E59: 80 | F59: 400 | G59: =IF(Prices!B18="","",Prices!B18) | H59: =IF(G59="","",E59/1000*G59) | I59: Purchase quote/specification required
A60: O-B08 | B60: Fish filling | C60: Main formula | D60: Oil | E60: 25 | F60: 125 | G60: =IF(Prices!B19="","",Prices!B19) | H60: =IF(G60="","",E60/1000*G60) | I60: PROVISIONAL 0.92 kg/L; correct after weighing
A61: O-B08 | B61: Fish filling | C61: Main formula | D61: Garlic peeled | E61: 10 | F61: 50 | G61: =IF(Prices!B20="","",Prices!B20) | H61: =IF(G61="","",E61/1000*G61) | I61: Purchase quote/specification required
A62: O-B08 | B62: Fish filling | C62: Main formula | D62: Ginger peeled | E62: 8 | F62: 40 | G62: =IF(Prices!B21="","",Prices!B21) | H62: =IF(G62="","",E62/1000*G62) | I62: Purchase quote/specification required
A63: O-B08 | B63: Fish filling | C63: Main formula | D63: Salt | E63: 5 | F63: 25 | G63: =IF(Prices!B6="","",Prices!B6) | H63: =IF(G63="","",E63/1000*G63) | I63: Owner price
A64: O-B08 | B64: Fish filling | C64: Main formula | D64: Black pepper | E64: 2 | F64: 10 | G64: =IF(Prices!B22="","",Prices!B22) | H64: =IF(G64="","",E64/1000*G64) | I64: Purchase quote/specification required
A65: O-B08 | B65: Fish filling | C65: Main formula | D65: Paprika | E65: 3 | F65: 15 | G65: =IF(Prices!B23="","",Prices!B23) | H65: =IF(G65="","",E65/1000*G65) | I65: Purchase quote/specification required
A66: O-B09 | B66: Beef pie filling | C66: Main formula | D66: Beef mince | E66: 500 | F66: 2500 | G66: =IF(Prices!B24="","",Prices!B24) | H66: =IF(G66="","",E66/1000*G66) | I66: Purchase quote/specification required
A67: O-B09 | B67: Beef pie filling | C67: Main formula | D67: Potato peeled | E67: 300 | F67: 1500 | G67: =IF(Prices!B25="","",Prices!B25) | H67: =IF(G67="","",E67/1000*G67) | I67: Purchase quote/specification required
A68: O-B09 | B68: Beef pie filling | C68: Main formula | D68: Carrot trimmed | E68: 150 | F68: 750 | G68: =IF(Prices!B18="","",Prices!B18) | H68: =IF(G68="","",E68/1000*G68) | I68: Purchase quote/specification required
A69: O-B09 | B69: Beef pie filling | C69: Main formula | D69: Onion trimmed | E69: 200 | F69: 1000 | G69: =IF(Prices!B17="","",Prices!B17) | H69: =IF(G69="","",E69/1000*G69) | I69: Purchase quote/specification required
A70: O-B09 | B70: Beef pie filling | C70: Main formula | D70: Oil | E70: 30 | F70: 150 | G70: =IF(Prices!B19="","",Prices!B19) | H70: =IF(G70="","",E70/1000*G70) | I70: PROVISIONAL 0.92 kg/L; correct after weighing
A71: O-B09 | B71: Beef pie filling | C71: Main formula | D71: Plain flour | E71: 35 | F71: 175 | G71: =IF(Prices!B14="","",Prices!B14) | H71: =IF(G71="","",E71/1000*G71) | I71: Purchase quote/specification required
A72: O-B09 | B72: Beef pie filling | C72: Main formula | D72: Water | E72: 250 | F72: 1250 | G72: =IF(Prices!B3="","",Prices!B3) | H72: =IF(G72="","",E72/1000*G72) | I72: Purchase quote/specification required
A73: O-B09 | B73: Beef pie filling | C73: Main formula | D73: Garlic peeled | E73: 12 | F73: 60 | G73: =IF(Prices!B20="","",Prices!B20) | H73: =IF(G73="","",E73/1000*G73) | I73: Purchase quote/specification required
A74: O-B09 | B74: Beef pie filling | C74: Main formula | D74: Ginger peeled | E74: 8 | F74: 40 | G74: =IF(Prices!B21="","",Prices!B21) | H74: =IF(G74="","",E74/1000*G74) | I74: Purchase quote/specification required
A75: O-B09 | B75: Beef pie filling | C75: Main formula | D75: Salt | E75: 12 | F75: 60 | G75: =IF(Prices!B6="","",Prices!B6) | H75: =IF(G75="","",E75/1000*G75) | I75: Owner price
A76: O-B09 | B76: Beef pie filling | C76: Main formula | D76: Black pepper | E76: 3 | F76: 15 | G76: =IF(Prices!B22="","",Prices!B22) | H76: =IF(G76="","",E76/1000*G76) | I76: Purchase quote/specification required
A77: O-B09 | B77: Beef pie filling | C77: Main formula | D77: Thyme | E77: 2 | F77: 10 | G77: =IF(Prices!B26="","",Prices!B26) | H77: =IF(G77="","",E77/1000*G77) | I77: Purchase quote/specification required
A78: O-B09 | B78: Beef pie filling | C78: Main formula | D78: Curry powder | E78: 4 | F78: 20 | G78: =IF(Prices!B27="","",Prices!B27) | H78: =IF(G78="","",E78/1000*G78) | I78: Purchase quote/specification required
A79: O-B10 | B79: Sausage roll filling | C79: Main formula | D79: Sausage meat | E79: 750 | F79: 3750 | G79: =IF(Prices!B28="","",Prices!B28) | H79: =IF(G79="","",E79/1000*G79) | I79: Purchase quote/specification required
A80: O-B10 | B80: Sausage roll filling | C80: Main formula | D80: Onion trimmed | E80: 100 | F80: 500 | G80: =IF(Prices!B17="","",Prices!B17) | H80: =IF(G80="","",E80/1000*G80) | I80: Purchase quote/specification required
A81: O-B10 | B81: Sausage roll filling | C81: Main formula | D81: Breadcrumbs | E81: 70 | F81: 350 | G81: =IF(Prices!B29="","",Prices!B29) | H81: =IF(G81="","",E81/1000*G81) | I81: Purchase quote/specification required
A82: O-B10 | B82: Sausage roll filling | C82: Main formula | D82: Egg | E82: 60 | F82: 300 | G82: =IF(Prices!B9="","",Prices!B9) | H82: =IF(G82="","",E82/1000*G82) | I82: Purchase quote/specification required
A83: O-B10 | B83: Sausage roll filling | C83: Main formula | D83: Garlic peeled | E83: 10 | F83: 50 | G83: =IF(Prices!B20="","",Prices!B20) | H83: =IF(G83="","",E83/1000*G83) | I83: Purchase quote/specification required
A84: O-B10 | B84: Sausage roll filling | C84: Main formula | D84: Black pepper | E84: 2 | F84: 10 | G84: =IF(Prices!B22="","",Prices!B22) | H84: =IF(G84="","",E84/1000*G84) | I84: Purchase quote/specification required
A85: O-B10 | B85: Sausage roll filling | C85: Main formula | D85: Paprika | E85: 3 | F85: 15 | G85: =IF(Prices!B23="","",Prices!B23) | H85: =IF(G85="","",E85/1000*G85) | I85: Purchase quote/specification required
A86: O-B10 | B86: Sausage roll filling | C86: Main formula | D86: Salt | E86: 5 | F86: 25 | G86: =IF(Prices!B6="","",Prices!B6) | H86: =IF(G86="","",E86/1000*G86) | I86: Owner price
A87: O-B11 | B87: Creamy chicken filling | C87: Main formula | D87: Chicken boneless | E87: 600 | F87: 3000 | G87: =IF(Prices!B30="","",Prices!B30) | H87: =IF(G87="","",E87/1000*G87) | I87: Purchase quote/specification required
A88: O-B11 | B88: Creamy chicken filling | C88: Main formula | D88: Potato peeled | E88: 150 | F88: 750 | G88: =IF(Prices!B25="","",Prices!B25) | H88: =IF(G88="","",E88/1000*G88) | I88: Purchase quote/specification required
A89: O-B11 | B89: Creamy chicken filling | C89: Main formula | D89: Carrot trimmed | E89: 100 | F89: 500 | G89: =IF(Prices!B18="","",Prices!B18) | H89: =IF(G89="","",E89/1000*G89) | I89: Purchase quote/specification required
A90: O-B11 | B90: Creamy chicken filling | C90: Main formula | D90: Onion trimmed | E90: 120 | F90: 600 | G90: =IF(Prices!B17="","",Prices!B17) | H90: =IF(G90="","",E90/1000*G90) | I90: Purchase quote/specification required
A91: O-B11 | B91: Creamy chicken filling | C91: Main formula | D91: Pepper trimmed | E91: 80 | F91: 400 | G91: =IF(Prices!B31="","",Prices!B31) | H91: =IF(G91="","",E91/1000*G91) | I91: Purchase quote/specification required
A92: O-B11 | B92: Creamy chicken filling | C92: Main formula | D92: Margarine | E92: 30 | F92: 150 | G92: =IF(Prices!B5="","",Prices!B5) | H92: =IF(G92="","",E92/1000*G92) | I92: Roma; fat, salt and application suitability unconfirmed
A93: O-B11 | B93: Creamy chicken filling | C93: Main formula | D93: Plain flour | E93: 45 | F93: 225 | G93: =IF(Prices!B14="","",Prices!B14) | H93: =IF(G93="","",E93/1000*G93) | I93: Purchase quote/specification required
A94: O-B11 | B94: Creamy chicken filling | C94: Main formula | D94: UHT milk | E94: 250 | F94: 1250 | G94: =IF(Prices!B32="","",Prices!B32) | H94: =IF(G94="","",E94/1000*G94) | I94: Purchase quote/specification required
A95: O-B11 | B95: Creamy chicken filling | C95: Main formula | D95: Water | E95: 100 | F95: 500 | G95: =IF(Prices!B3="","",Prices!B3) | H95: =IF(G95="","",E95/1000*G95) | I95: Purchase quote/specification required
A96: O-B11 | B96: Creamy chicken filling | C96: Main formula | D96: Garlic peeled | E96: 10 | F96: 50 | G96: =IF(Prices!B20="","",Prices!B20) | H96: =IF(G96="","",E96/1000*G96) | I96: Purchase quote/specification required
A97: O-B11 | B97: Creamy chicken filling | C97: Main formula | D97: Salt | E97: 12 | F97: 60 | G97: =IF(Prices!B6="","",Prices!B6) | H97: =IF(G97="","",E97/1000*G97) | I97: Owner price
A98: O-B11 | B98: Creamy chicken filling | C98: Main formula | D98: Black pepper | E98: 3 | F98: 15 | G98: =IF(Prices!B22="","",Prices!B22) | H98: =IF(G98="","",E98/1000*G98) | I98: Purchase quote/specification required
A99: O-B11 | B99: Creamy chicken filling | C99: Main formula | D99: Thyme | E99: 2 | F99: 10 | G99: =IF(Prices!B26="","",Prices!B26) | H99: =IF(G99="","",E99/1000*G99) | I99: Purchase quote/specification required
A100: O-B12 | B100: Egg roll dough | C100: Main formula | D100: Plain flour | E100: 1000 | F100: 5000 | G100: =IF(Prices!B14="","",Prices!B14) | H100: =IF(G100="","",E100/1000*G100) | I100: Purchase quote/specification required
...

Sheet Summary
A1: ID | B1: Recipe | C1: Input grams | D1: Usable basis grams | E1: Planned units | F1: Known ingredient subtotal | G1: Missing price line count | H1: Complete variable batch cost INPUT | I1: Selling price INPUT | J1: Full cost per unit | K1: Contribution per unit | L1: Original missing inputs
A2: O-B01 | B2: Family bread dough | C2: 1715 | D2: 1700 | F2: =SUMIF(Ingredients!A:A,A2,Ingredients!H:H) | G2: =COUNTIFS(Ingredients!A:A,A2,Ingredients!G:G,"") | J2: =IF(OR(H2="",E2="",E2=0),"",H2/E2) | K2: =IF(OR(J2="",I2=""),"",I2-J2) | L2: Water
A3: O-B02 | B3: Condensed milk bun dough | C3: 1895 | D3: 1870 | F3: =SUMIF(Ingredients!A:A,A3,Ingredients!H:H) | G3: =COUNTIFS(Ingredients!A:A,A3,Ingredients!G:G,"") | J3: =IF(OR(H3="",E3="",E3=0),"",H3/E3) | K3: =IF(OR(J3="",I3=""),"",I3-J3) | L3: Condensed milk; Egg; Vanilla; Water; Whole milk powder
A4: O-B03 | B4: Sweet potato milk bread dough | C4: 1812 | D4: 1790 | F4: =SUMIF(Ingredients!A:A,A4,Ingredients!H:H) | G4: =COUNTIFS(Ingredients!A:A,A4,Ingredients!G:G,"") | J4: =IF(OR(H4="",E4="",E4=0),"",H4/E4) | K4: =IF(OR(J4="",I4=""),"",I4-J4) | L4: Condensed milk; Sweet potato flour; Water; Whole milk powder
A5: O-B04 | B5: Yeast doughnut dough | C5: 1808 | D5: 1780 | F5: =SUMIF(Ingredients!A:A,A5,Ingredients!H:H) | G5: =COUNTIFS(Ingredients!A:A,A5,Ingredients!G:G,"") | J5: =IF(OR(H5="",E5="",E5=0),"",H5/E5) | K5: =IF(OR(J5="",I5=""),"",I5-J5) | L5: Egg; Nutmeg; Vanilla; Water; Whole milk powder
A6: O-B05 | B6: Puff puff batter | C6: 1846 | D6: 1830 | F6: =SUMIF(Ingredients!A:A,A6,Ingredients!H:H) | G6: =COUNTIFS(Ingredients!A:A,A6,Ingredients!G:G,"") | J6: =IF(OR(H6="",E6="",E6=0),"",H6/E6) | K6: =IF(OR(J6="",I6=""),"",I6-J6) | L6: Nutmeg; Plain flour; Water
A7: O-B06 | B7: Fish roll dough | C7: 1679 | D7: 1660 | F7: =SUMIF(Ingredients!A:A,A7,Ingredients!H:H) | G7: =COUNTIFS(Ingredients!A:A,A7,Ingredients!G:G,"") | J7: =IF(OR(H7="",E7="",E7=0),"",H7/E7) | K7: =IF(OR(J7="",I7=""),"",I7-J7) | L7: Nutmeg; Plain flour; Water; Whole milk powder
A8: O-B07 | B8: Shortcrust pie pastry | C8: 1773 | D8: 1740 | F8: =SUMIF(Ingredients!A:A,A8,Ingredients!H:H) | G8: =COUNTIFS(Ingredients!A:A,A8,Ingredients!G:G,"") | J8: =IF(OR(H8="",E8="",E8=0),"",H8/E8) | K8: =IF(OR(J8="",I8=""),"",I8-J8) | L8: Baking powder; Egg; Plain flour; Water
A9: O-B08 | B9: Fish filling | C9: 783 | D9: 700 | F9: =SUMIF(Ingredients!A:A,A9,Ingredients!H:H) | G9: =COUNTIFS(Ingredients!A:A,A9,Ingredients!G:G,"") | J9: =IF(OR(H9="",E9="",E9=0),"",H9/E9) | K9: =IF(OR(J9="",I9=""),"",I9-J9) | L9: Black pepper; Canned fish drained; Carrot trimmed; Garlic peeled; Ginger peeled; Onion trimmed; Paprika
A10: O-B09 | B10: Beef pie filling | C10: 1506 | D10: 1300 | F10: =SUMIF(Ingredients!A:A,A10,Ingredients!H:H) | G10: =COUNTIFS(Ingredients!A:A,A10,Ingredients!G:G,"") | J10: =IF(OR(H10="",E10="",E10=0),"",H10/E10) | K10: =IF(OR(J10="",I10=""),"",I10-J10) | L10: Beef mince; Black pepper; Carrot trimmed; Curry powder; Garlic peeled; Ginger peeled; Onion trimmed; Plain flour; Potato peeled; Thyme; Water
A11: O-B10 | B11: Sausage roll filling | C11: 1000 | D11: 980 | F11: =SUMIF(Ingredients!A:A,A11,Ingredients!H:H) | G11: =COUNTIFS(Ingredients!A:A,A11,Ingredients!G:G,"") | J11: =IF(OR(H11="",E11="",E11=0),"",H11/E11) | K11: =IF(OR(J11="",I11=""),"",I11-J11) | L11: Black pepper; Breadcrumbs; Egg; Garlic peeled; Onion trimmed; Paprika; Sausage meat
A12: O-B11 | B12: Creamy chicken filling | C12: 1502 | D12: 1300 | F12: =SUMIF(Ingredients!A:A,A12,Ingredients!H:H) | G12: =COUNTIFS(Ingredients!A:A,A12,Ingredients!G:G,"") | J12: =IF(OR(H12="",E12="",E12=0),"",H12/E12) | K12: =IF(OR(J12="",I12=""),"",I12-J12) | L12: Black pepper; Carrot trimmed; Chicken boneless; Garlic peeled; Onion trimmed; Pepper trimmed; Plain flour; Potato peeled; Thyme; UHT milk; Water
A13: O-B12 | B13: Egg roll dough | C13: 1674 | D13: 1650 | F13: =SUMIF(Ingredients!A:A,A13,Ingredients!H:H) | G13: =COUNTIFS(Ingredients!A:A,A13,Ingredients!G:G,"") | J13: =IF(OR(H13="",E13="",E13=0),"",H13/E13) | K13: =IF(OR(J13="",I13=""),"",I13-J13) | L13: Nutmeg; Plain flour; Water; Whole milk powder
... A37: O-B36 | B37: lemon-garlic oven fish | C37: 1081 | D37: 800 | F37: =SUMIF(Ingredients!A:A,A37,Ingredients!H:H) | G37: =COUNTIFS(Ingredients!A:A,A37,Ingredients!G:G,"") | J37: =IF(OR(H37="",E37="",E37=0),"",H37/E37) | K37: =IF(OR(J37="",I37=""),"",I37-J37) | L37: Black pepper; Boneless trimmed white fish; Garlic, finely crushed; Lemon juice; Paprika
A38: O-P01 | B38: Soft family bread | C38: 1700 | D38: 1700 | E38: 3 | F38: =SUMIF(Ingredients!A:A,A38,Ingredients!H:H) | G38: =COUNTIFS(Ingredients!A:A,A38,Ingredients!G:G,"") | J38: =IF(OR(H38="",E38="",E38=0),"",H38/E38) | K38: =IF(OR(J38="",I38=""),"",I38-J38) | L38: O-B01: Water
A39: O-P02 | B39: Condensed milk breakfast buns | C39: 1910 | D39: 1910 | E39: 20 | F39: =SUMIF(Ingredients!A:A,A39,Ingredients!H:H) | G39: =COUNTIFS(Ingredients!A:A,A39,Ingredients!G:G,"") | J39: =IF(OR(H39="",E39="",E39=0),"",H39/E39) | K39: =IF(OR(J39="",I39=""),"",I39-J39) | L39: Egg; O-B02: Condensed milk; O-B02: Egg; O-B02: Vanilla; O-B02: Water; O-B02: Whole milk powder
A40: O-P03 | B40: Nkambe sweet potato milk loaf | C40: 1790 | D40: 1790 | E40: 3 | F40: =SUMIF(Ingredients!A:A,A40,Ingredients!H:H) | G40: =COUNTIFS(Ingredients!A:A,A40,Ingredients!G:G,"") | J40: =IF(OR(H40="",E40="",E40=0),"",H40/E40) | K40: =IF(OR(J40="",I40=""),"",I40-J40) | L40: O-B03: Condensed milk; O-B03: Sweet potato flour; O-B03: Water; O-B03: Whole milk powder
A41: O-P04 | B41: Sugar ring doughnuts | C41: 2100 | D41: 2100 | E41: 25 | F41: =SUMIF(Ingredients!A:A,A41,Ingredients!H:H) | G41: =COUNTIFS(Ingredients!A:A,A41,Ingredients!G:G,"") | J41: =IF(OR(H41="",E41="",E41=0),"",H41/E41) | K41: =IF(OR(J41="",I41=""),"",I41-J41) | L41: O-B04: Egg; O-B04: Nutmeg; O-B04: Vanilla; O-B04: Water; O-B04: Whole milk powder
A42: O-P05 | B42: Puff puff | C42: 2010 | D42: 2010 | E42: 60 | F42: =SUMIF(Ingredients!A:A,A42,Ingredients!H:H) | G42: =COUNTIFS(Ingredients!A:A,A42,Ingredients!G:G,"") | J42: =IF(OR(H42="",E42="",E42=0),"",H42/E42) | K42: =IF(OR(J42="",I42=""),"",I42-J42) | L42: O-B05: Nutmeg; O-B05: Plain flour; O-B05: Water
A43: O-P06 | B43: Cameroon style fish rolls | C43: 2440 | D43: 2440 | E43: 24 | F43: =SUMIF(Ingredients!A:A,A43,Ingredients!H:H) | G43: =COUNTIFS(Ingredients!A:A,A43,Ingredients!G:G,"") | J43: =IF(OR(H43="",E43="",E43=0),"",H43/E43) | K43: =IF(OR(J43="",I43=""),"",I43-J43) | L43: O-B06: Nutmeg; O-B06: Plain flour; O-B06: Water; O-B06: Whole milk powder; O-B08: Black pepper; O-B08: Canned fish drained; O-B08: Carrot trimmed; O-B08: Garlic peeled; O-B08: Ginger peeled; O-B08: Onion trimmed; O-B08: Paprika
A44: O-P07 | B44: Beef meat pies | C44: 2885 | D44: 2885 | E44: 22 | F44: =SUMIF(Ingredients!A:A,A44,Ingredients!H:H) | G44: =COUNTIFS(Ingredients!A:A,A44,Ingredients!G:G,"") | J44: =IF(OR(H44="",E44="",E44=0),"",H44/E44) | K44: =IF(OR(J44="",I44=""),"",I44-J44) | L44: Egg; O-B07: Baking powder; O-B07: Egg; O-B07: Plain flour; O-B07: Water; O-B09: Beef mince; O-B09: Black pepper; O-B09: Carrot trimmed; O-B09: Curry powder; O-B09: Garlic peeled; O-B09: Ginger peeled; O-B09: Onion trimmed; O-B09: Plain flour; O-B09: Potato peeled; O-B09: Thyme; O-B09: Water
A45: O-P08 | B45: Sausage rolls | C45: 2745 | D45: 2745 | E45: 24 | F45: =SUMIF(Ingredients!A:A,A45,Ingredients!H:H) | G45: =COUNTIFS(Ingredients!A:A,A45,Ingredients!G:G,"") | J45: =IF(OR(H45="",E45="",E45=0),"",H45/E45) | K45: =IF(OR(J45="",I45=""),"",I45-J45) | L45: Egg; O-B07: Baking powder; O-B07: Egg; O-B07: Plain flour; O-B07: Water; O-B10: Black pepper; O-B10: Breadcrumbs; O-B10: Egg; O-B10: Garlic peeled; O-B10: Onion trimmed; O-B10: Paprika; O-B10: Sausage meat
A46: O-P09 | B46: Creamy chicken pies | C46: 3045 | D46: 3045 | E46: 21 | F46: =SUMIF(Ingredients!A:A,A46,Ingredients!H:H) | G46: =COUNTIFS(Ingredients!A:A,A46,Ingredients!G:G,"") | J46: =IF(OR(H46="",E46="",E46=0),"",H46/E46) | K46: =IF(OR(J46="",I46=""),"",I46-J46) | L46: Egg; O-B07: Baking powder; O-B07: Egg; O-B07: Plain flour; O-B07: Water; O-B11: Black pepper; O-B11: Carrot trimmed; O-B11: Chicken boneless; O-B11: Garlic peeled; O-B11: Onion trimmed; O-B11: Pepper trimmed; O-B11: Plain flour; O-B11: Potato peeled; O-B11: Thyme; O-B11: UHT milk; O-B11: Water
A47: O-P10 | B47: Whole egg dough rolls | C47: 2630 | D47: 2630 | E47: 16 | F47: =SUMIF(Ingredients!A:A,A47,Ingredients!H:H) | G47: =COUNTIFS(Ingredients!A:A,A47,Ingredients!G:G,"") | J47: =IF(OR(H47="",E47="",E47=0),"",H47/E47) | K47: =IF(OR(J47="",I47=""),"",I47-J47) | L47: O-B12: Nutmeg; O-B12: Plain flour; O-B12: Water; O-B12: Whole milk powder; O-B13: Egg
A48: O-P11 | B48: Banana condensed milk cake slices | C48: 3010 | D48: 3010 | E48: 24 | F48: =SUMIF(Ingredients!A:A,A48,Ingredients!H:H) | G48: =COUNTIFS(Ingredients!A:A,A48,Ingredients!G:G,"") | J48: =IF(OR(H48="",E48="",E48=0),"",H48/E48) | K48: =IF(OR(J48="",I48=""),"",I48-J48) | L48: O-B14: Baking powder; O-B14: Baking soda; O-B14: Banana peeled; O-B14: Cinnamon; O-B14: Condensed milk; O-B14: Egg; O-B14: Plain flour; O-B14: Vanilla
A49: O-P12 | B49: Personal chicken pizza | C49: 3450 | D49: 3450 | E49: 11 | F49: =SUMIF(Ingredients!A:A,A49,Ingredients!H:H) | G49: =COUNTIFS(Ingredients!A:A,A49,Ingredients!G:G,"") | J49: =IF(OR(H49="",E49="",E49=0),"",H49/E49) | K49: =IF(OR(J49="",I49=""),"",I49-J49) | L49: Mozzarella; O-B15: Water; O-B16: Black pepper; O-B16: Garlic peeled; O-B16: Onion trimmed; O-B16: Oregano; O-B16: Tomato trimmed; O-B18: Black pepper; O-B18: Chicken boneless; O-B18: Chili trimmed; O-B18: Cinnamon; O-B18: Coriander; O-B18: Cumin; O-B18: Garlic peeled; O-B18: Lemon juice; O-B18: Paprika; O-B18: Vinegar 5%; O-B18: Yogurt plain; Onion trimmed; Pepper trimmed
... A61: O-A04 | B61: Beef mini pizza — ten-unit pilot | C61: 3126.3158 | D61: 3126.3158 | E61: 10 | F61: =SUMIF(Ingredients!A:A,A61,Ingredients!H:H) | G61: =COUNTIFS(Ingredients!A:A,A61,Ingredients!G:G,"") | J61: =IF(OR(H61="",E61="",E61=0),"",H61/E61) | K61: =IF(OR(J61="",I61=""),"",I61-J61) | L61: Mozzarella; O-B15: Water; O-B16: Black pepper; O-B16: Garlic peeled; O-B16: Onion trimmed; O-B16: Oregano; O-B16: Tomato trimmed; O-B19: Beef boneless; O-B19: Black pepper; O-B19: Cinnamon; O-B19: Coriander; O-B19: Cumin; O-B19: Garlic peeled; O-B19: Lemon juice; O-B19: Onion trimmed; O-B19: Paprika; O-B19: Vinegar 5%; Onion; Sweet pepper
A62: O-FBASE1 | B62: Gravity soft serve vanilla trial mix | C62: 1000 | D62: 970 | F62: =SUMIF(Ingredients!A:A,A62,Ingredients!H:H) | G62: =COUNTIFS(Ingredients!A:A,A62,Ingredients!G:G,"") | J62: =IF(OR(H62="",E62="",E62=0),"",H62/E62) | K62: =IF(OR(J62="",I62=""),"",I62-J62) | L62: Condensed milk; Cream 35%; Glucose powder; Ice cream stabilizer blend; Skim milk powder; UHT milk; Vanilla
A63: O-FBASE2 | B63: Vanilla condensed milk popsicle mix | C63: 1000 | D63: 970 | F63: =SUMIF(Ingredients!A:A,A63,Ingredients!H:H) | G63: =COUNTIFS(Ingredients!A:A,A63,Ingredients!G:G,"") | J63: =IF(OR(H63="",E63="",E63=0),"",H63/E63) | K63: =IF(OR(J63="",I63=""),"",I63-J63) | L63: Condensed milk; Cream 35%; Ice cream stabilizer blend; Skim milk powder; UHT milk; Vanilla
A64: O-FBASE3 | B64: Pineapple fruit ice mix | C64: 1000 | D64: 970 | F64: =SUMIF(Ingredients!A:A,A64,Ingredients!H:H) | G64: =COUNTIFS(Ingredients!A:A,A64,Ingredients!G:G,"") | J64: =IF(OR(H64="",E64="",E64=0),"",H64/E64) | K64: =IF(OR(J64="",I64=""),"",I64-J64) | L64: Glucose powder; Ice cream stabilizer blend; Lemon juice; Pineapple puree pasteurized; Water
A65: O-FBASE4 | B65: Mango yogurt popsicle mix | C65: 1000 | D65: 970 | F65: =SUMIF(Ingredients!A:A,A65,Ingredients!H:H) | G65: =COUNTIFS(Ingredients!A:A,A65,Ingredients!G:G,"") | J65: =IF(OR(H65="",E65="",E65=0),"",H65/E65) | K65: =IF(OR(J65="",I65=""),"",I65-J65) | L65: Condensed milk; Ice cream stabilizer blend; Mango puree pasteurized; Water; Yogurt plain
A66: O-FBASE5 | B66: Chocolate sundae sauce | C66: 955 | D66: 900 | F66: =SUMIF(Ingredients!A:A,A66,Ingredients!H:H) | G66: =COUNTIFS(Ingredients!A:A,A66,Ingredients!G:G,"") | J66: =IF(OR(H66="",E66="",E66=0),"",H66/E66) | K66: =IF(OR(J66="",I66=""),"",I66-J66) | L66: Cocoa; Condensed milk; Vanilla; Water
A67: O-FBASE6 | B67: Soft sandwich cookies | C67: 1086 | D67: 900 | F67: =SUMIF(Ingredients!A:A,A67,Ingredients!H:H) | G67: =COUNTIFS(Ingredients!A:A,A67,Ingredients!G:G,"") | J67: =IF(OR(H67="",E67="",E67=0),"",H67/E67) | K67: =IF(OR(J67="",I67=""),"",I67-J67) | L67: Baking powder; Cocoa; Egg; Plain flour; Vanilla
A68: O-FBASE7 | B68: Chocolate dipping coating | C68: 1000 | D68: 980 | F68: =SUMIF(Ingredients!A:A,A68,Ingredients!H:H) | G68: =COUNTIFS(Ingredients!A:A,A68,Ingredients!G:G,"") | J68: =IF(OR(H68="",E68="",E68=0),"",H68/E68) | K68: =IF(OR(J68="",I68=""),"",I68-J68) | L68: Compound chocolate coating
A69: O-F01 | B69: Vanilla soft serve cup or cone | C69: 970 | D69: 970 | F69: =SUMIF(Ingredients!A:A,A69,Ingredients!H:H) | G69: =COUNTIFS(Ingredients!A:A,A69,Ingredients!G:G,"") | J69: =IF(OR(H69="",E69="",E69=0),"",H69/E69) | K69: =IF(OR(J69="",I69=""),"",I69-J69) | L69: O-FBASE1: Condensed milk; O-FBASE1: Cream 35%; O-FBASE1: Glucose powder; O-FBASE1: Ice cream stabilizer blend; O-FBASE1: Skim milk powder; O-FBASE1: UHT milk; O-FBASE1: Vanilla
A70: O-F02 | B70: Chocolate peanut sundae | C70: 750 | D70: 750 | F70: =SUMIF(Ingredients!A:A,A70,Ingredients!H:H) | G70: =COUNTIFS(Ingredients!A:A,A70,Ingredients!G:G,"") | J70: =IF(OR(H70="",E70="",E70=0),"",H70/E70) | K70: =IF(OR(J70="",I70=""),"",I70-J70) | L70: O-FBASE1: Condensed milk; O-FBASE1: Cream 35%; O-FBASE1: Glucose powder; O-FBASE1: Ice cream stabilizer blend; O-FBASE1: Skim milk powder; O-FBASE1: UHT milk; O-FBASE1: Vanilla; O-FBASE5: Cocoa; O-FBASE5: Condensed milk; O-FBASE5: Vanilla; O-FBASE5: Water; Peanut roasted
A71: O-F03 | B71: Chocolate milkshake | C71: 1450 | D71: 1450 | F71: =SUMIF(Ingredients!A:A,A71,Ingredients!H:H) | G71: =COUNTIFS(Ingredients!A:A,A71,Ingredients!G:G,"") | J71: =IF(OR(H71="",E71="",E71=0),"",H71/E71) | K71: =IF(OR(J71="",I71=""),"",I71-J71) | L71: O-FBASE1: Condensed milk; O-FBASE1: Cream 35%; O-FBASE1: Glucose powder; O-FBASE1: Ice cream stabilizer blend; O-FBASE1: Skim milk powder; O-FBASE1: UHT milk; O-FBASE1: Vanilla; O-FBASE5: Cocoa; O-FBASE5: Condensed milk; O-FBASE5: Vanilla; O-FBASE5: Water; UHT milk
A72: O-F04 | B72: Chocolate cookie ice cream sandwich | C72: 1100 | D72: 1100 | F72: =SUMIF(Ingredients!A:A,A72,Ingredients!H:H) | G72: =COUNTIFS(Ingredients!A:A,A72,Ingredients!G:G,"") | J72: =IF(OR(H72="",E72="",E72=0),"",H72/E72) | K72: =IF(OR(J72="",I72=""),"",I72-J72) | L72: O-FBASE1: Condensed milk; O-FBASE1: Cream 35%; O-FBASE1: Glucose powder; O-FBASE1: Ice cream stabilizer blend; O-FBASE1: Skim milk powder; O-FBASE1: UHT milk; O-FBASE1: Vanilla; O-FBASE6: Baking powder; O-FBASE6: Cocoa; O-FBASE6: Egg; O-FBASE6: Plain flour; O-FBASE6: Vanilla
A73: O-F05 | B73: Condensed milk popsicles | C73: 970 | D73: 970 | F73: =SUMIF(Ingredients!A:A,A73,Ingredients!H:H) | G73: =COUNTIFS(Ingredients!A:A,A73,Ingredients!G:G,"") | J73: =IF(OR(H73="",E73="",E73=0),"",H73/E73) | K73: =IF(OR(J73="",I73=""),"",I73-J73) | L73: O-FBASE2: Condensed milk; O-FBASE2: Cream 35%; O-FBASE2: Ice cream stabilizer blend; O-FBASE2: Skim milk powder; O-FBASE2: UHT milk; O-FBASE2: Vanilla
... A76: O-F08 | B76: Chocolate dipped peanut milk bar | C76: 890 | D76: 890 | F76: =SUMIF(Ingredients!A:A,A76,Ingredients!H:H) | G76: =COUNTIFS(Ingredients!A:A,A76,Ingredients!G:G,"") | J76: =IF(OR(H76="",E76="",E76=0),"",H76/E76) | K76: =IF(OR(J76="",I76=""),"",I76-J76) | L76: O-FBASE2: Condensed milk; O-FBASE2: Cream 35%; O-FBASE2: Ice cream stabilizer blend; O-FBASE2: Skim milk powder; O-FBASE2: UHT milk; O-FBASE2: Vanilla; O-FBASE7: Compound chocolate coating; Peanut roasted
A77: S-B01 | B77: Daily French-style baguette | C77: 1685 | D77: 1403.605 | E77: 5 | F77: =SUMIF(Ingredients!A:A,A77,Ingredients!H:H) | G77: =COUNTIFS(Ingredients!A:A,A77,Ingredients!G:G,"") | J77: =IF(OR(H77="",E77="",E77=0),"",H77/E77) | K77: =IF(OR(J77="",I77=""),"",I77-J77) | L77: Water
A78: S-B02 | B78: Kumba-style soft block loaf | C78: 1772 | D78: 1528.173 | E78: 4 | F78: =SUMIF(Ingredients!A:A,A78,Ingredients!H:H) | G78: =COUNTIFS(Ingredients!A:A,A78,Ingredients!G:G,"") | J78: =IF(OR(H78="",E78="",E78=0),"",H78/E78) | K78: =IF(OR(J78="",I78=""),"",I78-J78) | L78: Margarine 80%; Nutmeg; Skim milk powder; Water
A79: S-B03 | B79: True-butter pain beurre | C79: 1782 | D79: 1536.797 | E79: 6 | F79: =SUMIF(Ingredients!A:A,A79,Ingredients!H:H) | G79: =COUNTIFS(Ingredients!A:A,A79,Ingredients!G:G,"") | J79: =IF(OR(H79="",E79="",E79=0),"",H79/E79) | K79: =IF(OR(J79="",I79=""),"",I79-J79) | L79: Butter 82%; Water
A80: S-B04 | B80: Sandwich pan loaf / pain de mie | C80: 1770 | D80: 1561.14 | E80: 3 | F80: =SUMIF(Ingredients!A:A,A80,Ingredients!H:H) | G80: =COUNTIFS(Ingredients!A:A,A80,Ingredients!G:G,"") | J80: =IF(OR(H80="",E80="",E80=0),"",H80/E80) | K80: =IF(OR(J80="",I80=""),"",I80-J80) | L80: Skim milk powder; Water
A81: S-B05 | B81: Soft burger buns | C81: 1840 | D81: 1586.816 | E81: 20 | F81: =SUMIF(Ingredients!A:A,A81,Ingredients!H:H) | G81: =COUNTIFS(Ingredients!A:A,A81,Ingredients!G:G,"") | J81: =IF(OR(H81="",E81="",E81=0),"",H81/E81) | K81: =IF(OR(J81="",I81=""),"",I81-J81) | L81: Skim milk powder; Water; Whole egg
A82: S-B06 | B82: Professional 50%-butter brioche | C82: 2290 | D82: 1974.896 | E82: 5 | F82: =SUMIF(Ingredients!A:A,A82,Ingredients!H:H) | G82: =COUNTIFS(Ingredients!A:A,A82,Ingredients!G:G,"") | J82: =IF(OR(H82="",E82="",E82=0),"",H82/E82) | K82: =IF(OR(J82="",I82=""),"",I82-J82) | L82: Butter 82%; Vanilla; Whole egg; Whole milk 3.5%
A83: S-B07 | B83: Milk bread finger rolls / pain au lait | C83: 1870 | D83: 1612.688 | E83: 24 | F83: =SUMIF(Ingredients!A:A,A83,Ingredients!H:H) | G83: =COUNTIFS(Ingredients!A:A,A83,Ingredients!G:G,"") | J83: =IF(OR(H83="",E83="",E83=0),"",H83/E83) | K83: =IF(OR(J83="",I83=""),"",I83-J83) | L83: Butter 82%; Whole milk 3.5%
A84: S-P01 | B84: Yeast donuts: plain, glazed and beignets sucrés | C84: 1958 | D84: 1705.091 | E84: 30 | F84: =SUMIF(Ingredients!A:A,A84,Ingredients!H:H) | G84: =COUNTIFS(Ingredients!A:A,A84,Ingredients!G:G,"") | J84: =IF(OR(H84="",E84="",E84=0),"",H84/E84) | K84: =IF(OR(J84="",I84=""),"",I84-J84) | L84: Butter 82%; Skim milk powder; Vanilla; Water; Whole egg
A85: S-P02 | B85: Yeast puff-puff / beignets farine | C85: 1946 | D85: 1663.669 | E85: 60 | F85: =SUMIF(Ingredients!A:A,A85,Ingredients!H:H) | G85: =COUNTIFS(Ingredients!A:A,A85,Ingredients!G:G,"") | J85: =IF(OR(H85="",E85="",E85=0),"",H85/E85) | K85: =IF(OR(J85="",I85=""),"",I85-J85) | L85: Nutmeg; Water
A86: S-P03 | B86: Cameroonian cake-style beignets soufflés | C86: 2398 | D86: 2046.186 | E86: 40 | F86: =SUMIF(Ingredients!A:A,A86,Ingredients!H:H) | G86: =COUNTIFS(Ingredients!A:A,A86,Ingredients!G:G,"") | J86: =IF(OR(H86="",E86="",E86=0),"",H86/E86) | K86: =IF(OR(J86="",I86=""),"",I86-J86) | L86: Baking powder; Nutmeg; Plain flour; Vanilla; Whole egg; Whole milk 3.5%
A87: S-P04 | B87: Coconut butter biscuits | C87: 2160 | D87: 1905.12 | E87: 80 | F87: =SUMIF(Ingredients!A:A,A87,Ingredients!H:H) | G87: =COUNTIFS(Ingredients!A:A,A87,Ingredients!G:G,"") | J87: =IF(OR(H87="",E87="",E87=0),"",H87/E87) | K87: =IF(OR(J87="",I87=""),"",I87-J87) | L87: Butter 82%; Desiccated coconut; Icing sugar; Plain flour; Vanilla; Whole egg
A88: S-P05 | B88: Banana snack cake | C88: 3595 | D88: 3100.328 | E88: 32 | F88: =SUMIF(Ingredients!A:A,A88,Ingredients!H:H) | G88: =COUNTIFS(Ingredients!A:A,A88,Ingredients!G:G,"") | J88: =IF(OR(H88="",E88="",E88=0),"",H88/E88) | K88: =IF(OR(J88="",I88=""),"",I88-J88) | L88: Baking powder; Banana pulp; Cinnamon; Plain flour; Vanilla; Whole egg; Whole milk 3.5%
... A117: M1-B13 | B117: Soft baguette-style bread | C117: 1710 | D117: 1692.9 | E117: 5 | F117: =SUMIF(Ingredients!A:A,A117,Ingredients!H:H) | G117: =COUNTIFS(Ingredients!A:A,A117,Ingredients!G:G,"") | J117: =IF(OR(H117="",E117="",E117=0),"",H117/E117) | K117: =IF(OR(J117="",I117=""),"",I117-J117) | L117: Potable water
A118: T01 | B118: Rolled and cut cake doughnuts | C118: 1848.3333 | F118: =SUMIF(Ingredients!A:A,A118,Ingredients!H:H) | G118: =COUNTIFS(Ingredients!A:A,A118,Ingredients!G:G,"") | J118: =IF(OR(H118="",E118="",E118=0),"",H118/E118) | K118: =IF(OR(J118="",I118=""),"",I118-J118) | L118: HOLD; EDC unidentified; Baking powder double acting, EDC unidentified HOLD, Egg edible mass, Water
A119: H01 | B119: Agege style soft loaf | C119: 1800 | D119: 1764 | E119: 3 | F119: =SUMIF(Ingredients!A:A,A119,Ingredients!H:H) | G119: =COUNTIFS(Ingredients!A:A,A119,Ingredients!G:G,"") | J119: =IF(OR(H119="",E119="",E119=0),"",H119/E119) | K119: =IF(OR(J119="",I119=""),"",I119-J119) | L119: Water
A120: H02 | B120: Tangzhong milk loaf | C120: 1880 | D120: 1842.4 | E120: 3 | F120: =SUMIF(Ingredients!A:A,A120,Ingredients!H:H) | G120: =COUNTIFS(Ingredients!A:A,A120,Ingredients!G:G,"") | J120: =IF(OR(H120="",E120="",E120=0),"",H120/E120) | K120: =IF(OR(J120="",I120=""),"",I120-J120) | L120: Egg edible mass; Water
A121: H03 | B121: Open crumb ciabatta | C121: 1825 | D121: 1788.5 | E121: 7 | F121: =SUMIF(Ingredients!A:A,A121,Ingredients!H:H) | G121: =COUNTIFS(Ingredients!A:A,A121,Ingredients!G:G,"") | J121: =IF(OR(H121="",E121="",E121=0),"",H121/E121) | K121: =IF(OR(J121="",I121=""),"",I121-J121) | L121: Water
A122: H04 | B122: Fifty percent whole wheat loaf | C122: 1767 | D122: 1731.66 | E122: 3 | F122: =SUMIF(Ingredients!A:A,A122,Ingredients!H:H) | G122: =COUNTIFS(Ingredients!A:A,A122,Ingredients!G:G,"") | J122: =IF(OR(H122="",E122="",E122=0),"",H122/E122) | K122: =IF(OR(J122="",I122=""),"",I122-J122) | L122: Honey; Water; Whole wheat flour
A123: H05 | B123: Danisa style margarine biscuits | C123: 1975.7778 | F123: =SUMIF(Ingredients!A:A,A123,Ingredients!H:H) | G123: =COUNTIFS(Ingredients!A:A,A123,Ingredients!G:G,"") | J123: =IF(OR(H123="",E123="",E123=0),"",H123/E123) | K123: =IF(OR(J123="",I123=""),"",I123-J123) | L123: HOLD; EDC unidentified; EDC unidentified HOLD, Egg edible mass
A124: H06 | B124: Melto short margarine biscuits | C124: 1666 | D124: 1632.68 | E124: 65 | F124: =SUMIF(Ingredients!A:A,A124,Ingredients!H:H) | G124: =COUNTIFS(Ingredients!A:A,A124,Ingredients!G:G,"") | J124: =IF(OR(H124="",E124="",E124=0),"",H124/E124) | K124: =IF(OR(J124="",I124=""),"",I124-J124) | L124: Egg edible mass; Icing sugar
A125: H07 | B125: Milk shortbread biscuits | C125: 1876 | D125: 1838.48 | E125: 61 | F125: =SUMIF(Ingredients!A:A,A125,Ingredients!H:H) | G125: =COUNTIFS(Ingredients!A:A,A125,Ingredients!G:G,"") | J125: =IF(OR(H125="",E125="",E125=0),"",H125/E125) | K125: =IF(OR(J125="",I125=""),"",I125-J125) | L125: Egg edible mass; Icing sugar; Water
A126: H08 | B126: Marble pound cake | C126: 2064 | D126: 2022.72 | E126: 4 | F126: =SUMIF(Ingredients!A:A,A126,Ingredients!H:H) | G126: =COUNTIFS(Ingredients!A:A,A126,Ingredients!G:G,"") | J126: =IF(OR(H126="",E126="",E126=0),"",H126/E126) | K126: =IF(OR(J126="",I126=""),"",I126-J126) | L126: Baking powder double acting; Egg edible mass; Unsweetened cocoa; Vanilla extract; Water
A127: H09 | B127: Plain genoise sponge | C127: 1854 | D127: 1816.92 | E127: 4 | F127: =SUMIF(Ingredients!A:A,A127,Ingredients!H:H) | G127: =COUNTIFS(Ingredients!A:A,A127,Ingredients!G:G,"") | J127: =IF(OR(H127="",E127="",E127=0),"",H127/E127) | K127: =IF(OR(J127="",I127=""),"",I127-J127) | L127: Egg edible mass; Vanilla extract
A128: H10 | B128: Crisp chin chin | C128: 1810 | D128: 1773.8 | E128: 88 | F128: =SUMIF(Ingredients!A:A,A128,Ingredients!H:H) | G128: =COUNTIFS(Ingredients!A:A,A128,Ingredients!G:G,"") | J128: =IF(OR(H128="",E128="",E128=0),"",H128/E128) | K128: =IF(OR(J128="",I128=""),"",I128-J128) | L128: Baking powder double acting; Egg edible mass; Ground nutmeg; Water
A129: H11 | B129: Cake style beignets souffles | C129: 2352 | D129: 2304.96 | E129: 65 | F129: =SUMIF(Ingredients!A:A,A129,Ingredients!H:H) | G129: =COUNTIFS(Ingredients!A:A,A129,Ingredients!G:G,"") | J129: =IF(OR(H129="",E129="",E129=0),"",H129/E129) | K129: =IF(OR(J129="",I129=""),"",I129-J129) | L129: Baking powder double acting; Egg edible mass; Fresh lime zest; Pasteurized whole milk; Vanilla sugar
A130: H12 | B130: Laminated croissants | C130: 1975 | D130: 1935.5 | E130: 24 | F130: =SUMIF(Ingredients!A:A,A130,Ingredients!H:H) | G130: =COUNTIFS(Ingredients!A:A,A130,Ingredients!G:G,"") | J130: =IF(OR(H130="",E130="",E130=0),"",H130/E130) | K130: =IF(OR(J130="",I130=""),"",I130-J130) | L130: Qualified roll-in pastry fat; Water
A131: H13 | B131: Chocolate laminated rolls | C131: 1120 | D131: 1097.6 | E131: 9 | F131: =SUMIF(Ingredients!A:A,A131,Ingredients!H:H) | G131: =COUNTIFS(Ingredients!A:A,A131,Ingredients!G:G,"") | J131: =IF(OR(H131="",E131="",E131=0),"",H131/E131) | K131: =IF(OR(J131="",I131=""),"",I131-J131) | L131: Bake stable chocolate batons; H12: Qualified roll-in pastry fat; H12: Water
A132: H14 | B132: Local chocolate galette bread | C132: 1884 | D132: 1846.32 | E132: 18 | F132: =SUMIF(Ingredients!A:A,A132,Ingredients!H:H) | G132: =COUNTIFS(Ingredients!A:A,A132,Ingredients!G:G,"") | J132: =IF(OR(H132="",E132="",E132=0),"",H132/E132) | K132: =IF(OR(J132="",I132=""),"",I132-J132) | L132: Bake stable chocolate; Baking powder double acting; Egg edible mass; Water
A133: H15 | B133: Zebra chocolate milk loaf | C133: 2030 | D133: 1989.4 | E133: 3 | F133: =SUMIF(Ingredients!A:A,A133,Ingredients!H:H) | G133: =COUNTIFS(Ingredients!A:A,A133,Ingredients!G:G,"") | J133: =IF(OR(H133="",E133="",E133=0),"",H133/E133) | K133: =IF(OR(J133="",I133=""),"",I133-J133) | L133: Egg edible mass; Unsweetened cocoa; Water
A134: H16 | B134: Rosemary tray focaccia | C134: 1859 | D134: 1617.33 | E134: 10 | F134: =SUMIF(Ingredients!A:A,A134,Ingredients!H:H) | G134: =COUNTIFS(Ingredients!A:A,A134,Ingredients!G:G,"") | J134: =IF(OR(H134="",E134="",E134=0),"",H134/E134) | K134: =IF(OR(J134="",I134=""),"",I134-J134) | L134: Dried rosemary; Water
A135: H17 | B135: Thin plantain chips | C135: 1006 | D135: 452.7 | E135: 9 | F135: =SUMIF(Ingredients!A:A,A135,Ingredients!H:H) | G135: =COUNTIFS(Ingredients!A:A,A135,Ingredients!G:G,"") | J135: =IF(OR(H135="",E135="",E135=0),"",H135/E135) | K135: =IF(OR(J135="",I135=""),"",I135-J135) | L135: Peeled firm unripe plantain
A136: H18 | B136: Caramelized onion and cheese filling | C136: 1257 | D136: 905.04 | F136: =SUMIF(Ingredients!A:A,A136,Ingredients!H:H) | G136: =COUNTIFS(Ingredients!A:A,A136,Ingredients!G:G,"") | J136: =IF(OR(H136="",E136="",E136=0),"",H136/E136) | K136: =IF(OR(J136="",I136=""),"",I136-J136) | L136: Balsamic vinegar; Black pepper; Gruyere cheese; Peeled onions
A137: H19 | B137: Vanilla pastry cream | C137: 772 | D137: 748.84 | F137: =SUMIF(Ingredients!A:A,A137,Ingredients!H:H) | G137: =COUNTIFS(Ingredients!A:A,A137,Ingredients!G:G,"") | J137: =IF(OR(H137="",E137="",E137=0),"",H137/E137) | K137: =IF(OR(J137="",I137=""),"",I137-J137) | L137: Cornstarch; Pasteurized egg yolk; Pasteurized whole milk; Unsalted dairy butter; Vanilla extract
A138: H20 | B138: Honey oat and groundnut granola | C138: 856 | D138: 804.64 | E138: 26 | F138: =SUMIF(Ingredients!A:A,A138,Ingredients!H:H) | G138: =COUNTIFS(Ingredients!A:A,A138,Ingredients!G:G,"") | J138: =IF(OR(H138="",E138="",E138=0),"",H138/E138) | K138: =IF(OR(J138="",I138=""),"",I138-J138) | L138: Ground cinnamon; Honey; Ready-to-eat roasted groundnuts; Rolled oats
A139: BAG-H2-01 | B139: Direct-dough commercial baguette | C139: 12121.9 | D139: 12000.681 | E139: 39 | F139: =SUMIF(Ingredients!A:A,A139,Ingredients!H:H) | G139: =COUNTIFS(Ingredients!A:A,A139,Ingredients!G:G,"") | J139: =IF(OR(H139="",E139="",E139=0),"",H139/E139) | K139: =IF(OR(J139="",I139=""),"",I139-J139) | L139: Water; dusting and operating costs; pilot retained units include reject allowance

Sheet Coverage
A1: ID | B1: Name | C1: Record type | D1: Source | E1: Locator | F1: Status | G1: Decision or issue
A2: O-B01 | B2: Family bread dough | C2: Working card | D2: S163 | E2: lines 186-212 | F2: Harmonized source formulation — production trial required | G2: Retain the specified source formula because its ingredients, process and component routing are more explicit than the earlier drafts. Replace obsolete costs; use Nevada for the named instant yeast at the stated trial dose. Keep true butter, skim powder, whole powder and sweetened condensed milk specifications separate from the owner’s stocked substitutes.
A3: O-B02 | B3: Condensed milk bun dough | C3: Working card | D3: S163 | E3: lines 213-243 | F3: Harmonized source formulation — production trial required | G3: Retain the specified source formula because its ingredients, process and component routing are more explicit than the earlier drafts. Replace obsolete costs; use Nevada for the named instant yeast at the stated trial dose. Keep true butter, skim powder, whole powder and sweetened condensed milk specifications separate from the owner’s stocked substitutes.
A4: O-B03 | B4: Sweet potato milk bread dough | C4: Working card | D4: S163 | E4: lines 244-273 | F4: Harmonized source formulation — production trial required | G4: Retain the specified source formula because its ingredients, process and component routing are more explicit than the earlier drafts. Replace obsolete costs; use Nevada for the named instant yeast at the stated trial dose. Keep true butter, skim powder, whole powder and sweetened condensed milk specifications separate from the owner’s stocked substitutes.
A5: O-B04 | B5: Yeast doughnut dough | C5: Working card | D5: S163 | E5: lines 274-304 | F5: Harmonized source formulation — production trial required | G5: Retain the specified source formula because its ingredients, process and component routing are more explicit than the earlier drafts. Replace obsolete costs; use Nevada for the named instant yeast at the stated trial dose. Keep true butter, skim powder, whole powder and sweetened condensed milk specifications separate from the owner’s stocked substitutes.
A6: O-B05 | B6: Puff puff batter | C6: Working card | D6: S163 | E6: lines 305-331 | F6: Harmonized source formulation — production trial required | G6: Retain the specified source formula because its ingredients, process and component routing are more explicit than the earlier drafts. Replace obsolete costs; use Nevada for the named instant yeast at the stated trial dose. Keep true butter, skim powder, whole powder and sweetened condensed milk specifications separate from the owner’s stocked substitutes.
A7: O-B06 | B7: Fish roll dough | C7: Working card | D7: S163 | E7: lines 332-360 | F7: Harmonized source formulation — production trial required | G7: Retain the specified source formula because its ingredients, process and component routing are more explicit than the earlier drafts. Replace obsolete costs; use Nevada for the named instant yeast at the stated trial dose. Keep true butter, skim powder, whole powder and sweetened condensed milk specifications separate from the owner’s stocked substitutes.
A8: O-B07 | B8: Shortcrust pie pastry | C8: Working card | D8: S163 | E8: lines 361-387 | F8: Harmonized source formulation — production trial required | G8: Retain the specified source formula because its ingredients, process and component routing are more explicit than the earlier drafts. Replace obsolete costs; use Nevada for the named instant yeast at the stated trial dose. Keep true butter, skim powder, whole powder and sweetened condensed milk specifications separate from the owner’s stocked substitutes.
A9: O-B08 | B9: Fish filling | C9: Working card | D9: S163 | E9: lines 388-415 | F9: Harmonized source formulation — production trial required | G9: Retain the specified source formula because its ingredients, process and component routing are more explicit than the earlier drafts. Replace obsolete costs; use Nevada for the named instant yeast at the stated trial dose. Keep true butter, skim powder, whole powder and sweetened condensed milk specifications separate from the owner’s stocked substitutes.
A10: O-B09 | B10: Beef pie filling | C10: Working card | D10: S163 | E10: lines 416-447 | F10: Harmonized source formulation — production trial required | G10: Retain the specified source formula because its ingredients, process and component routing are more explicit than the earlier drafts. Replace obsolete costs; use Nevada for the named instant yeast at the stated trial dose. Keep true butter, skim powder, whole powder and sweetened condensed milk specifications separate from the owner’s stocked substitutes.
A11: O-B10 | B11: Sausage roll filling | C11: Working card | D11: S163 | E11: lines 448-474 | F11: Harmonized source formulation — production trial required | G11: Retain the specified source formula because its ingredients, process and component routing are more explicit than the earlier drafts. Replace obsolete costs; use Nevada for the named instant yeast at the stated trial dose. Keep true butter, skim powder, whole powder and sweetened condensed milk specifications separate from the owner’s stocked substitutes.
A12: O-B11 | B12: Creamy chicken filling | C12: Working card | D12: S163 | E12: lines 475-506 | F12: Harmonized source formulation — production trial required | G12: Retain the specified source formula because its ingredients, process and component routing are more explicit than the earlier drafts. Replace obsolete costs; use Nevada for the named instant yeast at the stated trial dose. Keep true butter, skim powder, whole powder and sweetened condensed milk specifications separate from the owner’s stocked substitutes.
... A797: PLAN-BAG-H | B797: 800 raw-piece campaign | C797: Production scenario | D797: S038; S026; S027 | E797: H2 baguette planning chapter | F797: Conditional proposed programme | G797: Not an additional recipe; resources and times require commissioning

Sheet Original formulas
A1: Variant ID | B1: Sheet | C1: Source | D1: Cell | E1: Ingredient | F1: Original g | G1: Cell value/formula | H1: Working alternative
A2: L001 | B2: Baguette AI | C2: S132 | D2: 'Baguette AI'!C5,D5 | E2: flour | F2: 18000 | G2: 18000 | H2: M1-B12 / M1-B13 / S-B01
A3: L001 | B3: Baguette AI | C3: S132 | D3: 'Baguette AI'!C6,D6 | E3: yeast | F3: 100 | G3: 100 | H3: M1-B12 / M1-B13 / S-B01
A4: L001 | B4: Baguette AI | C4: S132 | D4: 'Baguette AI'!C7,D7 | E4: salt | F4: 350 | G4: 350 | H4: M1-B12 / M1-B13 / S-B01
A5: L001 | B5: Baguette AI | C5: S132 | D5: 'Baguette AI'!C8,D8 | E5: ice water | F5: 12000 | G5: 12000 | H5: M1-B12 / M1-B13 / S-B01
A6: L001 | B6: Baguette AI | C6: S132 | D6: 'Baguette AI'!C9,D9 | E6: improver | F6: 70 | G6: 70 | H6: M1-B12 / M1-B13 / S-B01
A7: L002 | B7: Baguette AI | C7: S132 | D7: 'Baguette AI'!C5,F5 | E7: flour | F7: 350 | G7: 350 | H7: M1-B12 / M1-B13 / S-B01
A8: L002 | B8: Baguette AI | C8: S132 | D8: 'Baguette AI'!C6,F6 | E8: yeast | F8: 2 | G8: 2 | H8: M1-B12 / M1-B13 / S-B01
A9: L002 | B9: Baguette AI | C9: S132 | D9: 'Baguette AI'!C7,F7 | E9: salt | F9: 10 | G9: 10 | H9: M1-B12 / M1-B13 / S-B01
A10: L002 | B10: Baguette AI | C10: S132 | D10: 'Baguette AI'!C8,F8 | E10: ice water | F10: 210 | G10: 210 | H10: M1-B12 / M1-B13 / S-B01
A11: L002 | B11: Baguette AI | C11: S132 | D11: 'Baguette AI'!C9,F9 | E11: improver | F11: 20 | G11: 20 | H11: M1-B12 / M1-B13 / S-B01
A12: L003 | B12: Banh Mi | C12: S132 | D12: 'Banh Mi'!C5,D5 | E12: flour | F12: 120000 | G12: =F5*20 [cached: 120000] | H12: M1-B13; distinct Banh Mi trial remains open
A13: L003 | B13: Banh Mi | C13: S132 | D13: 'Banh Mi'!C6,D6 | E13: yeast | F13: 1800 | G13: =F6*20 [cached: 1800] | H13: M1-B13; distinct Banh Mi trial remains open
... A2411: L254 | B2411: YUMMY YOGHOURT (YUYO) | C2411: S143 | D2411: 'YUMMY YOGHOURT (YUYO)'!C9,L9 | E2411: vanilla | F2411: 37.5 | G2411: =F9/10 [cached: 37.5] | H2411: S-Y01–S-Y03

Sheet Issues
A1: ID | B1: Issue class | C1: Finding | D1: Required action
A2: O-B01 | B2: Production validation | C2: No signed repeat-batch evidence supplied | D2: Record three independent trials, quality, yield, safety and full cost before release
A3: O-B02 | B3: Production validation | C3: No signed repeat-batch evidence supplied | D3: Record three independent trials, quality, yield, safety and full cost before release
A4: O-B03 | B4: Production validation | C4: No signed repeat-batch evidence supplied | D4: Record three independent trials, quality, yield, safety and full cost before release
A5: O-B04 | B5: Production validation | C5: No signed repeat-batch evidence supplied | D5: Record three independent trials, quality, yield, safety and full cost before release
A6: O-B05 | B6: Production validation | C6: No signed repeat-batch evidence supplied | D6: Record three independent trials, quality, yield, safety and full cost before release
A7: O-B06 | B7: Production validation | C7: No signed repeat-batch evidence supplied | D7: Record three independent trials, quality, yield, safety and full cost before release
A8: O-B07 | B8: Production validation | C8: No signed repeat-batch evidence supplied | D8: Record three independent trials, quality, yield, safety and full cost before release
A9: O-B08 | B9: Production validation | C9: No signed repeat-batch evidence supplied | D9: Record three independent trials, quality, yield, safety and full cost before release
A10: O-B09 | B10: Production validation | C10: No signed repeat-batch evidence supplied | D10: Record three independent trials, quality, yield, safety and full cost before release
A11: O-B10 | B11: Production validation | C11: No signed repeat-batch evidence supplied | D11: Record three independent trials, quality, yield, safety and full cost before release
A12: O-B11 | B12: Production validation | C12: No signed repeat-batch evidence supplied | D12: Record three independent trials, quality, yield, safety and full cost before release
... A815: H05 | B815: EDC identity correction | C815: S132 Danisa lists 9,000 g workbook butter and 50 g EDC per 18 kg flour. Roma margarine is 500 g and EDC is 2.7778 g per 1 kg flour. Other rounded H2 inputs are retained. The former 503 g margarine combined and rounded two different ingredients. EDC is not butter and must not be treated or priced as margarine. Its identity, specification, permitted application, dose and purchase price remain unresolved. Keep EDC as a separate historical ingredient and hold affected formulas until it is identified. The earlier owner-workbook butter-to-margarine instruction remains separate; true dairy butter in independent recipes retains its specification. Milk tantalizer and improver remain omitted from revised recipes. | D815: Hold recipe; identify EDC and complete method and cost

Sheet Sources
A1: Source ID | B1: Title | C1: Full path | D1: Format | E1: Modified date | F1: Bytes | G1: SHA256 | H1: Readability/disposition | I1: Role | J1: Production-test evidence | K1: Language screening | L1: Stated version | M1: Extraction extent
A2: S001 | B2: bakery_strategy_and_recipe_manual_updated.pdf | C2: C:\Users\J COMPUTER\Documents\Codex\2026-09-12\x20-go\docs\bakery\bakery_strategy_and_recipe_manual_updated.pdf | D2: .pdf | E2: 2026-09-12T17:07:02.777893+00:00 | F2: 113921 | G2: 74c7cccf472d4b37c1cb045a39225838a2f871d2451ae2183124f64ab6f6c93f | H2: Extracted text | I2: Related edition, supporting context or superseded source; no independent trial inferred | J2: No owner production trial log found | K2: English (text screening) | L2: No explicit version established; modified date is file metadata only | M2: 10 extracted pages/blocks/rows; 72 recipe keyword signals (not recipe count)
A3: S002 | B3: bakery_strategy_and_recipe_manual.md | C3: C:\Users\J COMPUTER\Documents\Codex\2026-09-12\x20-go\outputs\bakery_strategy_and_recipe_manual.md | D3: .md | E3: 2026-09-12T17:02:51.066689+00:00 | F3: 41737 | G3: dbba9e528b1c8f3130bf52762b5f2e5e0f0c06fbb2155e33a80814eb0bb78713 | H3: Extracted text | I3: Related edition, supporting context or superseded source; no independent trial inferred | J3: No owner production trial log found | K3: English (text screening) | L3: No explicit version established; modified date is file metadata only | M3: 797 extracted pages/blocks/rows; 60 recipe keyword signals (not recipe count)
B4: bakery_strategy_and_recipe_manual.docx | C4: C:\Users\J COMPUTER\Documents\Codex\2026-09-12\x20-go\work\bakery_strategy_and_recipe_manual.docx | D4: .docx | E4: 2026-09-12T17:06:54.130905+00:00 | F4: 59173 | H4: Generated work or software support file | I4: Filename screened | J4: No owner production trial log found | K4: Not established / non-text | L4: No explicit version established; modified date is file metadata only | M4: extracted pages/blocks/rows; recipe keyword signals (not recipe count)
B5: bakery_strategy_and_recipe_manual.pdf | C5: C:\Users\J COMPUTER\Documents\Codex\2026-09-12\x20-go\work\rendered_manual\bakery_strategy_and_recipe_manual.pdf | D5: .pdf | E5: 2026-09-12T17:07:02.777893+00:00 | F5: 113921 | H5: Generated work or software support file | I5: Filename screened | J5: No owner production trial log found | K5: Not established / non-text | L5: No explicit version established; modified date is file metadata only | M5: extracted pages/blocks/rows; recipe keyword signals (not recipe count)
A6: S003 | B6: bakery_strategy_and_recipe_manual.md | C6: C:\Users\J COMPUTER\Documents\Codex\2026-09-12\x20-using-this-document-download-the\docs\bakery\bakery_strategy_and_recipe_manual.md | D6: .md | E6: 2026-09-13T12:08:59.616137+00:00 | F6: 79733 | G6: 4b982269e1d209a62ba8a1800c1b5d847cec607f75b9ea2dde4485121509da08 | H6: Extracted text | I6: Related edition, supporting context or superseded source; no independent trial inferred | J6: No owner production trial log found | K6: English (text screening) | L6: No explicit version established; modified date is file metadata only | M6: 1146 extracted pages/blocks/rows; 95 recipe keyword signals (not recipe count)
A7: S004 | B7: bakery_strategy_and_recipe_manual.pdf | C7: C:\Users\J COMPUTER\Documents\Codex\2026-09-12\x20-using-this-document-download-the\docs\bakery\bakery_strategy_and_recipe_manual.pdf | D7: .pdf | E7: 2026-09-13T12:20:16.996575+00:00 | F7: 312562 | G7: 095af6506a0ddc0d20a6a3cf2e718e609f8fa2def8d26f99a97c75bba7c05746 | H7: Extracted text | I7: Related edition, supporting context or superseded source; no independent trial inferred | J7: No owner production trial log found | K7: English (text screening) | L7: No explicit version established; modified date is file metadata only | M7: 45 extracted pages/blocks/rows; 171 recipe keyword signals (not recipe count)
A8: S005 | B8: Equipment_Gaps_and_Trial_Plan.md | C8: C:\Users\J COMPUTER\Documents\Codex\2026-09-12\x20-using-this-document-download-the\docs\bakery\Equipment_Gaps_and_Trial_Plan.md | D8: .md | E8: 2026-09-13T21:16:23.614072+00:00 | F8: 11936 | G8: 887013ce03097c8cd0e2d559dd8b6f369f6a6e0827b8b35a7aecfa2807f4036a | H8: Extracted text | I8: Related edition, supporting context or superseded source; no independent trial inferred | J8: No owner production trial log found | K8: English (text screening) | L8: No explicit version established; modified date is file metadata only | M8: 74 extracted pages/blocks/rows; 15 recipe keyword signals (not recipe count)
A9: S006 | B9: Nkambe_Bakery_Strategy_and_Recipe_Manual.md | C9: C:\Users\J COMPUTER\Documents\Codex\2026-09-12\x20-using-this-document-download-the\docs\bakery\Nkambe_Bakery_Strategy_and_Recipe_Manual.md | D9: .md | E9: 2026-09-14T14:11:17.347165+00:00 | F9: 215633 | G9: c2449e2d412be100e03097e99d865502306b185c2ac475686f0bdd05aee806aa | H9: Extracted text | I9: Related edition, supporting context or superseded source; no independent trial inferred | J9: No owner production trial log found | K9: English (text screening) | L9: No explicit version established; modified date is file metadata only | M9: 2697 extracted pages/blocks/rows; 375 recipe keyword signals (not recipe count)
A10: S007 | B10: Nkambe_Bakery_Strategy_and_Recipe_Manual.pdf | C10: C:\Users\J COMPUTER\Documents\Codex\2026-09-12\x20-using-this-document-download-the\docs\bakery\Nkambe_Bakery_Strategy_and_Recipe_Manual.pdf | D10: .pdf | E10: 2026-09-14T14:11:36.397636+00:00 | F10: 428291 | G10: 1ff70f54a43346e89057c30486c799af12e845502adaa43fd3ebfc20cf5d24e9 | H10: Extracted text | I10: Related edition, supporting context or superseded source; no independent trial inferred | J10: No owner production trial log found | K10: English (text screening) | L10: No explicit version established; modified date is file metadata only | M10: 89 extracted pages/blocks/rows; 466 recipe keyword signals (not recipe count)
A11: S008 | B11: Product_Selection_and_Costing.xlsx | C11: C:\Users\J COMPUTER\Documents\Codex\2026-09-12\x20-using-this-document-download-the\docs\bakery\Product_Selection_and_Costing.xlsx | D11: .xlsx | E11: 2026-09-13T21:02:47.391404+00:00 | F11: 75646 | G11: 5935cf2783344af2e6912671a4edd7fdc04d241e00487c5cc048fff60c471587 | H11: Extracted text | I11: Related edition, supporting context or superseded source; no independent trial inferred | J11: No owner production trial log found | K11: English (text screening) | L11: No explicit version established; modified date is file metadata only | M11: 631 extracted pages/blocks/rows; 40 recipe keyword signals (not recipe count)
A12: S005 | B12: Equipment_Gaps_and_Trial_Plan.md | C12: C:\Users\J COMPUTER\Documents\Codex\2026-09-12\x20-using-this-document-download-the\docs\bakery\research-edition\Equipment_Gaps_and_Trial_Plan.md | D12: .md | E12: 2026-09-13T21:16:23.614072+00:00 | F12: 11936 | G12: 887013ce03097c8cd0e2d559dd8b6f369f6a6e0827b8b35a7aecfa2807f4036a | H12: Exact duplicate | I12: Related edition, supporting context or superseded source; no independent trial inferred | J12: No owner production trial log found | K12: English (text screening) | L12: No explicit version established; modified date is file metadata only | M12: extracted pages/blocks/rows; recipe keyword signals (not recipe count)
A13: S006 | B13: Nkambe_Bakery_Strategy_and_Recipe_Manual.md | C13: C:\Users\J COMPUTER\Documents\Codex\2026-09-12\x20-using-this-document-download-the\docs\bakery\research-edition\Nkambe_Bakery_Strategy_and_Recipe_Manual.md | D13: .md | E13: 2026-09-14T14:11:17.347165+00:00 | F13: 215633 | G13: c2449e2d412be100e03097e99d865502306b185c2ac475686f0bdd05aee806aa | H13: Exact duplicate | I13: Related edition, supporting context or superseded source; no independent trial inferred | J13: No owner production trial log found | K13: English (text screening) | L13: No explicit version established; modified date is file metadata only | M13: extracted pages/blocks/rows; recipe keyword signals (not recipe count)
A14: S007 | B14: Nkambe_Bakery_Strategy_and_Recipe_Manual.pdf | C14: C:\Users\J COMPUTER\Documents\Codex\2026-09-12\x20-using-this-document-download-the\docs\bakery\research-edition\Nkambe_Bakery_Strategy_and_Recipe_Manual.pdf | D14: .pdf | E14: 2026-09-14T14:11:36.397636+00:00 | F14: 428291 | G14: 1ff70f54a43346e89057c30486c799af12e845502adaa43fd3ebfc20cf5d24e9 | H14: Exact duplicate | I14: Related edition, supporting context or superseded source; no independent trial inferred | J14: No owner production trial log found | K14: English (text screening) | L14: No explicit version established; modified date is file metadata only | M14: extracted pages/blocks/rows; recipe keyword signals (not recipe count)
A15: S009 | B15: Product_Selection_and_Costing.xlsx | C15: C:\Users\J COMPUTER\Documents\Codex\2026-09-12\x20-using-this-document-download-the\docs\bakery\research-edition\Product_Selection_and_Costing.xlsx | D15: .xlsx | E15: 2026-09-14T20:11:44.845456+00:00 | F15: 87464 | G15: 692365afec02ade7ab75bf2a2534a6f3cbea000009b7b7dcb95679ccd4bffa68 | H15: Extracted text | I15: Related edition, supporting context or superseded source; no independent trial inferred | J15: No owner production trial log found | K15: English (text screening) | L15: No explicit version established; modified date is file metadata only | M15: 631 extracted pages/blocks/rows; 40 recipe keyword signals (not recipe count)
A16: S010 | B16: Research_Sources_and_Evidence.md | C16: C:\Users\J COMPUTER\Documents\Codex\2026-09-12\x20-using-this-document-download-the\docs\bakery\research-edition\Research_Sources_and_Evidence.md | D16: .md | E16: 2026-09-14T14:11:17.375622+00:00 | F16: 15552 | G16: c4931fb1f6acb269edc18f1a2fb642bc594bbc4ccb0afb48898ec35a34bf9041 | H16: Extracted text | I16: Related edition, supporting context or superseded source; no independent trial inferred | J16: No owner production trial log found | K16: English (text screening) | L16: No explicit version established; modified date is file metadata only | M16: 292 extracted pages/blocks/rows; 7 recipe keyword signals (not recipe count)
A17: S011 | B17: Revision_and_Verification_Report.md | C17: C:\Users\J COMPUTER\Documents\Codex\2026-09-12\x20-using-this-document-download-the\docs\bakery\research-edition\Revision_and_Verification_Report.md | D17: .md | E17: 2026-09-14T14:13:48.143033+00:00 | F17: 14340 | G17: 6cb443dad8899af30c5d089ae1b9ce5e1ed2790a9d28e3f5004054d79a3107a3 | H17: Extracted text | I17: Related edition, supporting context or superseded source; no independent trial inferred | J17: No owner production trial log found | K17: English (text screening) | L17: No explicit version established; modified date is file metadata only | M17: 85 extracted pages/blocks/rows; 22 recipe keyword signals (not recipe count)
... A19: S011 | B19: Revision_and_Verification_Report.md | C19: C:\Users\J COMPUTER\Documents\Codex\2026-09-12\x20-using-this-document-download-the\docs\bakery\Revision_and_Verification_Report.md | D19: .md | E19: 2026-09-14T14:13:48.143033+00:00 | F19: 14340 | G19: 6cb443dad8899af30c5d089ae1b9ce5e1ed2790a9d28e3f5004054d79a3107a3 | H19: Exact duplicate | I19: Related edition, supporting context or superseded source; no independent trial inferred | J19: No owner production trial log found | K19: English (text screening) | L19: No explicit version established; modified date is file metadata only | M19: extracted pages/blocks/rows; recipe keyword signals (not recipe count)
B20: bakery_manual_before_redesign.pdf | C20: C:\Users\J COMPUTER\Documents\Codex\2026-09-12\x20-using-this-document-download-the\work\bakery_design_review\bakery_manual_before_redesign.pdf | D20: .pdf | E20: 2026-09-13T12:09:27.201531+00:00 | F20: 160616 | H20: Generated work or software support file | I20: Filename screened | J20: No owner production trial log found | K20: Not established / non-text | L20: No explicit version established; modified date is file metadata only | M20: extracted pages/blocks/rows; recipe keyword signals (not recipe count)
B21: bakery_strategy_and_recipe_manual.pdf | C21: C:\Users\J COMPUTER\Documents\Codex\2026-09-12\x20-using-this-document-download-the\work\bakery_design_review\bakery_strategy_and_recipe_manual.pdf | D21: .pdf | E21: 2026-09-13T12:20:16.996575+00:00 | F21: 312562 | H21: Generated work or software support file | I21: Filename screened | J21: No owner production trial log found | K21: Not established / non-text | L21: No explicit version established; modified date is file metadata only | M21: extracted pages/blocks/rows; recipe keyword signals (not recipe count)
B22: contact_1.jpg | C22: C:\Users\J COMPUTER\Documents\Codex\2026-09-12\x20-using-this-document-download-the\work\bakery_design_review\contact_1.jpg | D22: .jpg | E22: 2026-09-13T12:20:20.239397+00:00 | F22: 184113 | H22: Generated work or software support file | I22: Filename screened | J22: No owner production trial log found | K22: Not established / non-text | L22: No explicit version established; modified date is file metadata only | M22: extracted pages/blocks/rows; recipe keyword signals (not recipe count)
B23: contact_2.jpg | C23: C:\Users\J COMPUTER\Documents\Codex\2026-09-12\x20-using-this-document-download-the\work\bakery_design_review\contact_2.jpg | D23: .jpg | E23: 2026-09-13T12:20:20.252282+00:00 | F23: 221509 | H23: Generated work or software support file | I23: Filename screened | J23: No owner production trial log found | K23: Not established / non-text | L23: No explicit version established; modified date is file metadata only | M23: extracted pages/blocks/rows; recipe keyword signals (not recipe count)
B24: contact_3.jpg | C24: C:\Users\J COMPUTER\Documents\Codex\2026-09-12\x20-using-this-document-download-the\work\bakery_design_review\contact_3.jpg | D24: .jpg | E24: 2026-09-13T12:20:20.261636+00:00 | F24: 262077 | H24: Generated work or software support file | I24: Filename screened | J24: No owner production trial log found | K24: Not established / non-text | L24: No explicit version established; modified date is file metadata only | M24: extracted pages/blocks/rows; recipe keyword signals (not recipe count)
B25: contact_4.jpg | C25: C:\Users\J COMPUTER\Documents\Codex\2026-09-12\x20-using-this-document-download-the\work\bakery_design_review\contact_4.jpg | D25: .jpg | E25: 2026-09-13T12:20:20.280204+00:00 | F25: 163483 | H25: Generated work or software support file | I25: Filename screened | J25: No owner production trial log found | K25: Not established / non-text | L25: No explicit version established; modified date is file metadata only | M25: extracted pages/blocks/rows; recipe keyword signals (not recipe count)
B26: contact_5.jpg | C26: C:\Users\J COMPUTER\Documents\Codex\2026-09-12\x20-using-this-document-download-the\work\bakery_design_review\contact_5.jpg | D26: .jpg | E26: 2026-09-13T12:16:36.370112+00:00 | F26: 83177 | H26: Generated work or software support file | I26: Filename screened | J26: No owner production trial log found | K26: Not established / non-text | L26: No explicit version established; modified date is file metadata only | M26: extracted pages/blocks/rows; recipe keyword signals (not recipe count)
B27: page_01.png | C27: C:\Users\J COMPUTER\Documents\Codex\2026-09-12\x20-using-this-document-download-the\work\bakery_design_review\page_01.png | D27: .png | E27: 2026-09-13T12:20:18.003646+00:00 | F27: 107700 | H27: Generated work or software support file | I27: Filename screened | J27: No owner production trial log found | K27: Not established / non-text | L27: No explicit version established; modified date is file metadata only | M27: extracted pages/blocks/rows; recipe keyword signals (not recipe count)
B28: page_02.png | C28: C:\Users\J COMPUTER\Documents\Codex\2026-09-12\x20-using-this-document-download-the\work\bakery_design_review\page_02.png | D28: .png | E28: 2026-09-13T12:20:18.048571+00:00 | F28: 101258 | H28: Generated work or software support file | I28: Filename screened | J28: No owner production trial log found | K28: Not established / non-text | L28: No explicit version established; modified date is file metadata only | M28: extracted pages/blocks/rows; recipe keyword signals (not recipe count)
B29: page_03.png | C29: C:\Users\J COMPUTER\Documents\Codex\2026-09-12\x20-using-this-document-download-the\work\bakery_design_review\page_03.png | D29: .png | E29: 2026-09-13T12:20:18.100704+00:00 | F29: 102723 | H29: Generated work or software support file | I29: Filename screened | J29: No owner production trial log found | K29: Not established / non-text | L29: No explicit version established; modified date is file metadata only | M29: extracted pages/blocks/rows; recipe keyword signals (not recipe count)
B30: page_04.png | C30: C:\Users\J COMPUTER\Documents\Codex\2026-09-12\x20-using-this-document-download-the\work\bakery_design_review\page_04.png | D30: .png | E30: 2026-09-13T12:20:18.147408+00:00 | F30: 101540 | H30: Generated work or software support file | I30: Filename screened | J30: No owner production trial log found | K30: Not established / non-text | L30: No explicit version established; modified date is file metadata only | M30: extracted pages/blocks/rows; recipe keyword signals (not recipe count)
B31: page_05.png | C31: C:\Users\J COMPUTER\Documents\Codex\2026-09-12\x20-using-this-document-download-the\work\bakery_design_review\page_05.png | D31: .png | E31: 2026-09-13T12:20:18.198012+00:00 | F31: 163772 | H31: Generated work or software support file | I31: Filename screened | J31: No owner production trial log found | K31: Not established / non-text | L31: No explicit version established; modified date is file metadata only | M31: extracted pages/blocks/rows; recipe keyword signals (not recipe count)
... B86: Staggered_Baguette_Production_Schedule.pdf.txt | C86: C:\Users\J COMPUTER\Documents\Codex\2026-09-12\x20-using-this-document-download-the\work\research_review\Staggered_Baguette_Production_Schedule.pdf.txt | D86: .txt | E86: 2026-09-13T20:38:03.592762+00:00 | F86: 3833 | H86: Generated work or software support file | I86: Filename screened | J86: No owner production trial log found | K86: Not established / non-text | L86: No explicit version established; modified date is file metadata only | M86: extracted pages/blocks/rows; recipe keyword signals (not recipe count)
A87: S012 | B87: Nkambe_Bakery_Business_Report_Partial.pdf | C87: C:\Users\J COMPUTER\Documents\Codex\2026-10-01\referenced-chatgpt-conversation-this-is-an\outputs\Nkambe_Bakery_Business_Report_Partial.pdf | D87: .pdf | E87: 2026-10-03T09:28:58.150452+00:00 | F87: 140585 | G87: 92619ed7f32b4f682ed206490adf5e7aff3eed8588b4511bd938dd8ea0067ca5 | H87: Extracted text | I87: Related edition, supporting context or superseded source; no independent trial inferred | J87: No owner production trial log found | K87: English (text screening) | L87: No explicit version established; modified date is file metadata only | M87: 21 extracted pages/blocks/rows; 45 recipe keyword signals (not recipe count)
A88: S013 | B88: Nkambe_Bakery_Product_Development_and_Profitability_Strategy.pdf | C88: C:\Users\J COMPUTER\Documents\Codex\2026-10-08\referenced-chatgpt-conversation-this-is-an-2\outputs\Nkambe_Bakery_Product_Development_and_Profitability_Strategy.pdf | D88: .pdf | E88: 2026-10-08T12:08:08.212843+00:00 | F88: 118715 | G88: e8f97c198f48cc035c0576d1a468fb627c37ddc51d0f8658281053a950ac8b84 | H88: Extracted text | I88: Recipe source or technical context included | J88: No owner production trial log found | K88: English (text screening) | L88: No explicit version established; modified date is file metadata only | M88: 20 extracted pages/blocks/rows; 14 recipe keyword signals (not recipe count)
A89: S014 | B89: Nkambe_Recipe_Manual_Module_1_Breads_and_Baguettes.pdf | C89: C:\Users\J COMPUTER\Documents\Codex\2026-10-08\referenced-chatgpt-conversation-this-is-an-2\outputs\Nkambe_Recipe_Manual_Module_1_Breads_and_Baguettes.pdf | D89: .pdf | E89: 2026-10-08T16:19:26.752118+00:00 | F89: 255392 | G89: febe5a7bf8d9cea610fec8a88ad2c460e2b05ae840503f43cdaa2108825f62b6 | H89: Extracted text | I89: Related edition, supporting context or superseded source; no independent trial inferred | J89: No owner production trial log found | K89: English (text screening) | L89: Version 0.1 | M89: 58 extracted pages/blocks/rows; 476 recipe keyword signals (not recipe count)
A90: S015 | B90: Nkambe_Recipe_Manual_Module_1_Editable.rtf | C90: C:\Users\J COMPUTER\Documents\Codex\2026-10-08\referenced-chatgpt-conversation-this-is-an-2\outputs\Nkambe_Recipe_Manual_Module_1_Editable.rtf | D90: .rtf | E90: 2026-10-08T16:19:26.909838+00:00 | F90: 605141 | G90: 431588d64dc6ca3cfcb1728b95e7550c78742871c47a62781017bb47627463c3 | H90: Editable companion; PDF version used for reading | I90: Related edition, supporting context or superseded source; no independent trial inferred | J90: No owner production trial log found | K90: Not established / non-text | L90: No explicit version established; modified date is file metadata only | M90: 0 extracted pages/blocks/rows; 0 recipe keyword signals (not recipe count)
A91: S016 | B91: Nkambe_Recipe_Manual_Module_1_Updated_v0_2.pdf | C91: C:\Users\J COMPUTER\Documents\Codex\2026-10-08\referenced-chatgpt-conversation-this-is-an-2\outputs\Nkambe_Recipe_Manual_Module_1_Updated_v0_2.pdf | D91: .pdf | E91: 2026-10-08T16:51:20.521805+00:00 | F91: 268930 | G91: 8993fc4142bba42747a6df9f5e00550f0c7f36c871cc6b74ab564d2a2625fa9b | H91: Extracted text | I91: Recipe source or technical context included | J91: No owner production trial log found | K91: English (text screening) | L91: Version 0.2 | M91: 62 extracted pages/blocks/rows; 481 recipe keyword signals (not recipe count)
A92: S017 | B92: Nkambe_Recipe_Manual_Module_1_Updated_v0_2.rtf | C92: C:\Users\J COMPUTER\Documents\Codex\2026-10-08\referenced-chatgpt-conversation-this-is-an-2\outputs\Nkambe_Recipe_Manual_Module_1_Updated_v0_2.rtf | D92: .rtf | E92: 2026-10-08T16:51:20.681172+00:00 | F92: 671805 | G92: 7d367ef28b6f4c1a335b69311e27e0f752cd28d520b9463ed9387a5362bdd16f | H92: Editable companion; PDF version used for reading | I92: Related edition, supporting context or superseded source; no independent trial inferred | J92: No owner production trial log found | K92: Not established / non-text | L92: No explicit version established; modified date is file metadata only | M92: 0 extracted pages/blocks/rows; 0 recipe keyword signals (not recipe count)
B93: contact-1.jpg | C93: C:\Users\J COMPUTER\Documents\Codex\2026-10-08\referenced-chatgpt-conversation-this-is-an-2\work\bread_manual\contact-1.jpg | D93: .jpg | E93: 2026-10-08T16:20:12.228607+00:00 | F93: 184767 | H93: Generated work or software support file | I93: Filename screened | J93: No owner production trial log found | K93: Not established / non-text | L93: No explicit version established; modified date is file metadata only | M93: extracted pages/blocks/rows; recipe keyword signals (not recipe count)
B94: contact-2.jpg | C94: C:\Users\J COMPUTER\Documents\Codex\2026-10-08\referenced-chatgpt-conversation-this-is-an-2\work\bread_manual\contact-2.jpg | D94: .jpg | E94: 2026-10-08T16:20:12.946915+00:00 | F94: 252203 | H94: Generated work or software support file | I94: Filename screened | J94: No owner production trial log found | K94: Not established / non-text | L94: No explicit version established; modified date is file metadata only | M94: extracted pages/blocks/rows; recipe keyword signals (not recipe count)
B95: contact-3.jpg | C95: C:\Users\J COMPUTER\Documents\Codex\2026-10-08\referenced-chatgpt-conversation-this-is-an-2\work\bread_manual\contact-3.jpg | D95: .jpg | E95: 2026-10-08T16:20:13.689389+00:00 | F95: 248191 | H95: Generated work or software support file | I95: Filename screened | J95: No owner production trial log found | K95: Not established / non-text | L95: No explicit version established; modified date is file metadata only | M95: extracted pages/blocks/rows; recipe keyword signals (not recipe count)
B96: contact-4.jpg | C96: C:\Users\J COMPUTER\Documents\Codex\2026-10-08\referenced-chatgpt-conversation-this-is-an-2\work\bread_manual\contact-4.jpg | D96: .jpg | E96: 2026-10-08T16:20:14.406659+00:00 | F96: 248128 | H96: Generated work or software support file | I96: Filename screened | J96: No owner production trial log found | K96: Not established / non-text | L96: No explicit version established; modified date is file metadata only | M96: extracted pages/blocks/rows; recipe keyword signals (not recipe count)
B97: contact-5.jpg | C97: C:\Users\J COMPUTER\Documents\Codex\2026-10-08\referenced-chatgpt-conversation-this-is-an-2\work\bread_manual\contact-5.jpg | D97: .jpg | E97: 2026-10-08T16:20:14.979314+00:00 | F97: 203368 | H97: Generated work or software support file | I97: Filename screened | J97: No owner production trial log found | K97: Not established / non-text | L97: No explicit version established; modified date is file metadata only | M97: extracted pages/blocks/rows; recipe keyword signals (not recipe count)
B98: contact-6.jpg | C98: C:\Users\J COMPUTER\Documents\Codex\2026-10-08\referenced-chatgpt-conversation-this-is-an-2\work\bread_manual\contact-6.jpg | D98: .jpg | E98: 2026-10-08T16:15:56.829590+00:00 | F98: 215471 | H98: Generated work or software support file | I98: Filename screened | J98: No owner production trial log found | K98: Not established / non-text | L98: No explicit version established; modified date is file metadata only | M98: extracted pages/blocks/rows; recipe keyword signals (not recipe count)
B99: contact-7.jpg | C99: C:\Users\J COMPUTER\Documents\Codex\2026-10-08\referenced-chatgpt-conversation-this-is-an-2\work\bread_manual\contact-7.jpg | D99: .jpg | E99: 2026-10-08T16:15:57.595649+00:00 | F99: 206346 | H99: Generated work or software support file | I99: Filename screened | J99: No owner production trial log found | K99: Not established / non-text | L99: No explicit version established; modified date is file metadata only | M99: extracted pages/blocks/rows; recipe keyword signals (not recipe count)
B100: contact-8.jpg | C100: C:\Users\J COMPUTER\Documents\Codex\2026-10-08\referenced-chatgpt-conversation-this-is-an-2\work\bread_manual\contact-8.jpg | D100: .jpg | E100: 2026-10-08T16:15:57.701958+00:00 | F100: 58706 | H100: Generated work or software support file | I100: Filename screened | J100: No owner production trial log found | K100: Not established / non-text | L100: No explicit version established; modified date is file metadata only | M100: extracted pages/blocks/rows; recipe keyword signals (not recipe count)
B101: manual_source.md | C101: C:\Users\J COMPUTER\Documents\Codex\2026-10-08\referenced-chatgpt-conversation-this-is-an-2\work\bread_manual\manual_source.md | D101: .md | E101: 2026-10-08T16:19:26.918816+00:00 | F101: 155084 | H101: Generated work or software support file | I101: Filename screened | J101: No owner production trial log found | K101: Not established / non-text | L101: No explicit version established; modified date is file metadata only | M101: extracted pages/blocks/rows; recipe keyword signals (not recipe count)
B102: pdf_text.txt | C102: C:\Users\J COMPUTER\Documents\Codex\2026-10-08\referenced-chatgpt-conversation-this-is-an-2\work\bread_manual\pdf_text.txt | D102: .txt | E102: 2026-10-08T16:19:30.486109+00:00 | F102: 156042 | H102: Generated work or software support file | I102: Filename screened | J102: No owner production trial log found | K102: Not established / non-text | L102: No explicit version established; modified date is file metadata only | M102: extracted pages/blocks/rows; recipe keyword signals (not recipe count)
B103: contact-1.jpg | C103: C:\Users\J COMPUTER\Documents\Codex\2026-10-08\referenced-chatgpt-conversation-this-is-an-2\work\bread_manual_v02\contact-1.jpg | D103: .jpg | E103: 2026-10-08T16:51:59.432927+00:00 | F103: 185545 | H103: Generated work or software support file | I103: Filename screened | J103: No owner production trial log found | K103: Not established / non-text | L103: No explicit version established; modified date is file metadata only | M103: extracted pages/blocks/rows; recipe keyword signals (not recipe count)
B104: contact-2.jpg | C104: C:\Users\J COMPUTER\Documents\Codex\2026-10-08\referenced-chatgpt-conversation-this-is-an-2\work\bread_manual_v02\contact-2.jpg | D104: .jpg | E104: 2026-10-08T16:52:00.153435+00:00 | F104: 238563 | H104: Generated work or software support file | I104: Filename screened | J104: No owner production trial log found | K104: Not established / non-text | L104: No explicit version established; modified date is file metadata only | M104: extracted pages/blocks/rows; recipe keyword signals (not recipe count)
... B110: pdf_text.txt | C110: C:\Users\J COMPUTER\Documents\Codex\2026-10-08\referenced-chatgpt-conversation-this-is-an-2\work\bread_manual_v02\pdf_text.txt | D110: .txt | E110: 2026-10-08T16:51:24.804869+00:00 | F110: 164251 | H110: Generated work or software support file | I110: Filename screened | J110: No owner production trial log found | K110: Not established / non-text | L110: No explicit version established; modified date is file metadata only | M110: extracted pages/blocks/rows; recipe keyword signals (not recipe count)
A111: S018 | B111: Cameroon_Bakery_Technical_Report.md | C111: C:\Users\J COMPUTER\Documents\Codex\2026-10-08\referenced-chatgpt-conversation-this-is-an\outputs\Cameroon_Bakery_Technical_Report.md | D111: .md | E111: 2026-10-08T12:23:24.903728+00:00 | F111: 132284 | G111: 1dfc7e343c6d2baf3b835149bb601871d6d27059222c4f4557b696b784bf0512 | H111: Extracted text | I111: Recipe source or technical context included | J111: No owner production trial log found | K111: English (text screening) | L111: No explicit version established; modified date is file metadata only | M111: 1192 extracted pages/blocks/rows; 35 recipe keyword signals (not recipe count)
A112: S019 | B112: Cameroon_Bakery_Technical_Report.pdf | C112: C:\Users\J COMPUTER\Documents\Codex\2026-10-08\referenced-chatgpt-conversation-this-is-an\outputs\Cameroon_Bakery_Technical_Report.pdf | D112: .pdf | E112: 2026-10-08T12:29:11.693516+00:00 | F112: 256963 | G112: 3969ecc3b021b9d5e042b5f5986ff8b86185845ec923e7cb5e9c248ec4b7674d | H112: Extracted text | I112: Related edition, supporting context or superseded source; no independent trial inferred | J112: No owner production trial log found | K112: English (text screening) | L112: No explicit version established; modified date is file metadata only | M112: 55 extracted pages/blocks/rows; 35 recipe keyword signals (not recipe count)
A113: S020 | B113: 21+1 Recettes de glace italiennes douces et crémeuses pour Machine à Glace Italienne _ Le Guide Complet (Revision 1).pdf | C113: C:\Users\J COMPUTER\Downloads\21+1 Recettes de glace italiennes douces et crémeuses pour Machine à Glace Italienne _ Le Guide Complet (Revision 1).pdf | D113: .pdf | E113: 2026-07-28T05:30:01.688744+00:00 | F113: 1014362 | G113: 25fd0c270e36987055351627aa7c53fa0691a38516e78228604e6a02dcade103 | H113: Extracted text | I113: Recipe source or technical context included | J113: No owner production trial log found | K113: French (text screening) | L113: No explicit version established; modified date is file metadata only | M113: 44 extracted pages/blocks/rows; 19 recipe keyword signals (not recipe count)
A114: S021 | B114: 35. BAKERY EQUIPMENT quotation to kouatchoua mark 20260601 (1).pdf | C114: C:\Users\J COMPUTER\Downloads\35. BAKERY EQUIPMENT quotation to kouatchoua mark 20260601 (1).pdf | D114: .pdf | E114: 2026-06-01T08:37:59.560441+00:00 | F114: 291914 | G114: 901ded47d0b7c66f675a85927f6fc0ce6f54b883163d8aeeb2f51109f2830cd1 | H114: Extracted text | I114: Equipment/purchase context only; not proof of installed specification | J114: No owner production trial log found | K114: Not established / non-text | L114: No explicit version established; modified date is file metadata only | M114: 1 extracted pages/blocks/rows; 0 recipe keyword signals (not recipe count)
A115: S022 | B115: 35. BAKERY EQUIPMENT quotation to Rachad ZATO GARBA 20260516 (1).pdf | C115: C:\Users\J COMPUTER\Downloads\35. BAKERY EQUIPMENT quotation to Rachad ZATO GARBA 20260516 (1).pdf | D115: .pdf | E115: 2026-05-22T12:41:10.526783+00:00 | F115: 229008 | G115: ce676a717adbf8c4f42c8d99d924c97a0f6fe933f0aef0ad26403ee3d1647e6a | H115: Extracted text | I115: Equipment/purchase context only; not proof of installed specification | J115: No owner production trial log found | K115: Not established / non-text | L115: No explicit version established; modified date is file metadata only | M115: 1 extracted pages/blocks/rows; 0 recipe keyword signals (not recipe count)
A116: S023 | B116: 555736575-La-Patisserie.pdf | C116: C:\Users\J COMPUTER\Downloads\555736575-La-Patisserie.pdf | D116: .pdf | E116: 2026-08-24T16:40:39.220155+00:00 | F116: 110658519 | G116: 7e37e75a026a50a01406e1cbe886bf6f31f609608e1765d410433ecd858ffe93 | H116: Locally OCR recovered; adopted quantities require image check | I116: Recipe source or technical context included | J116: No owner production trial log found | K116: Not established / non-text | L116: No explicit version established; modified date is file metadata only | M116: 228 extracted pages/blocks/rows; 0 recipe keyword signals (not recipe count)
A117: S024 | B117: Bakery_Empire_Master_Operations_Manual (1).pdf | C117: C:\Users\J COMPUTER\Downloads\Bakery_Empire_Master_Operations_Manual (1).pdf | D117: .pdf | E117: 2026-09-11T16:54:08.916317+00:00 | F117: 12105 | G117: 46a528981a7b8d2a0ad93a0d12e12eee374c70e345df7c9de4ee740ac240b501 | H117: Extracted text | I117: Related edition, supporting context or superseded source; no independent trial inferred | J117: No owner production trial log found | K117: English (text screening) | L117: No explicit version established; modified date is file metadata only | M117: 5 extracted pages/blocks/rows; 8 recipe keyword signals (not recipe count)
A118: S025 | B118: Bakery_Empire_Master_Operations_Manual (2).pdf | C118: C:\Users\J COMPUTER\Downloads\Bakery_Empire_Master_Operations_Manual (2).pdf | D118: .pdf | E118: 2026-09-11T16:56:41.168424+00:00 | F118: 32229 | G118: 932b0e956856e9421f11a71c2fa2a862b50407d87f283486b1b7482eb3205e3a | H118: Extracted text | I118: Related edition, supporting context or superseded source; no independent trial inferred | J118: No owner production trial log found | K118: English (text screening) | L118: No explicit version established; modified date is file metadata only | M118: 14 extracted pages/blocks/rows; 37 recipe keyword signals (not recipe count)
A119: S026 | B119: Bakery_Empire_Master_Operations_Manual.md | C119: C:\Users\J COMPUTER\Downloads\Bakery_Empire_Master_Operations_Manual.md | D119: .md | E119: 2026-09-11T16:52:44.908908+00:00 | F119: 30612 | G119: bd9ffdd707fe608bab36c72360a290be418df67e27e8b625d61ad94a861007b6 | H119: Extracted text | I119: H2 five-batch scheduling companion; original 101-piece and timetable claims audited | J119: No owner production trial log found | K119: English (text screening) | L119: No explicit version established; modified date is file metadata only | M119: 245 extracted pages/blocks/rows; 31 recipe keyword signals (not recipe count)
A120: S027 | B120: Bakery_Empire_Master_Operations_Manual.pdf | C120: C:\Users\J COMPUTER\Downloads\Bakery_Empire_Master_Operations_Manual.pdf | D120: .pdf | E120: 2026-09-11T16:27:02.758401+00:00 | F120: 10652 | G120: 1d02155b06ffa4777a41cfdab99a47dc53fcbc8b1aa963c08b1a92063b53fef5 | H120: Extracted text | I120: H2 five-batch scheduling companion; original 101-piece and timetable claims audited | J120: No owner production trial log found | K120: English (text screening) | L120: No explicit version established; modified date is file metadata only | M120: 4 extracted pages/blocks/rows; 7 recipe keyword signals (not recipe count)
A121: S028 | B121: Cameroon_Bakery_Empire_Master_Guide.pdf | C121: C:\Users\J COMPUTER\Downloads\Cameroon_Bakery_Empire_Master_Guide.pdf | D121: .pdf | E121: 2026-09-11T15:49:45.652618+00:00 | F121: 23817 | G121: 8776f25d63513701a6a3d72a4d4d28009938fd091802f0207a47848897827597 | H121: Extracted text | I121: Related edition, supporting context or superseded source; no independent trial inferred | J121: No owner production trial log found | K121: English (text screening) | L121: No explicit version established; modified date is file metadata only | M121: 10 extracted pages/blocks/rows; 32 recipe keyword signals (not recipe count)
A122: S029 | B122: cameroon_bakery_high_value_recipes.pdf | C122: C:\Users\J COMPUTER\Downloads\cameroon_bakery_high_value_recipes.pdf | D122: .pdf | E122: 2026-10-01T13:41:52.130100+00:00 | F122: 16749 | G122: c1e351d255b996875eb6f165b188b9b10fa2b61f1b1381533c2cd5658168bc4a | H122: Extracted text | I122: Related edition, supporting context or superseded source; no independent trial inferred | J122: No owner production trial log found | K122: English (text screening) | L122: No explicit version established; modified date is file metadata only | M122: 6 extracted pages/blocks/rows; 28 recipe keyword signals (not recipe count)
... A124: S030 | B124: Commercial_Baguette_Production_Guide.pdf | C124: C:\Users\J COMPUTER\Downloads\Commercial_Baguette_Production_Guide.pdf | D124: .pdf | E124: 2026-09-11T13:38:00.699475+00:00 | F124: 5645 | G124: 2a4de593eb4a75c55067bccc628f86b51da4f59de06dc23016ddae00f59fc0bb | H124: Extracted text | I124: Recipe source or technical context included | J124: No owner production trial log found | K124: English (text screening) | L124: No explicit version established; modified date is file metadata only | M124: 2 extracted pages/blocks/rows; 4 recipe keyword signals (not recipe count)
A125: I01 | B125: food.com-recipe-copycat-mc-donalds-hamburgers-cheeseburgers-116181.jpeg | C125: C:\Users\J COMPUTER\Downloads\food.com-recipe-copycat-mc-donalds-hamburgers-cheeseburgers-116181.jpeg | D125: .jpeg | E125: 2025-07-27T12:45:24.870129+00:00 | F125: 251601 | H125: Visually screened relevant images; original preserved | I125: Image screening: burger reference, workbook screenshot or equipment photo; unrelated exam images excluded | J125: No owner production trial log found | K125: Not established / non-text | L125: No explicit version established; modified date is file metadata only | M125: extracted pages/blocks/rows; recipe keyword signals (not recipe count)
A126: S031 | B126: Les Meilleures Recettes de Bâtonnets Made in Africa (2) (1).pdf | C126: C:\Users\J COMPUTER\Downloads\Les Meilleures Recettes de Bâtonnets Made in Africa (2) (1).pdf | D126: .pdf | E126: 2026-07-31T11:44:22.206967+00:00 | F126: 2144582 | G126: babd46226ae382261dba4b9f1b1eae935f9cdd530e236cdcb91d3aae2cfb2505 | H126: Extracted text | I126: Recipe source or technical context included | J126: No owner production trial log found | K126: French (text screening) | L126: No explicit version established; modified date is file metadata only | M126: 46 extracted pages/blocks/rows; 44 recipe keyword signals (not recipe count)
A127: S032 | B127: nkambe_bakery_commercial_blueprint (1).pdf | C127: C:\Users\J COMPUTER\Downloads\nkambe_bakery_commercial_blueprint (1).pdf | D127: .pdf | E127: 2026-10-01T14:08:51.082457+00:00 | F127: 22578 | G127: b70fd7de5432877ead4f1fd31c93885558ed81eb65017b576a0c3136c8c95cb5 | H127: Extracted text | I127: Related edition, supporting context or superseded source; no independent trial inferred | J127: No owner production trial log found | K127: English (text screening) | L127: No explicit version established; modified date is file metadata only | M127: 9 extracted pages/blocks/rows; 42 recipe keyword signals (not recipe count)
A128: S032 | B128: nkambe_bakery_commercial_blueprint (2).pdf | C128: C:\Users\J COMPUTER\Downloads\nkambe_bakery_commercial_blueprint (2).pdf | D128: .pdf | E128: 2026-10-01T14:12:01.183678+00:00 | F128: 22578 | G128: b70fd7de5432877ead4f1fd31c93885558ed81eb65017b576a0c3136c8c95cb5 | H128: Exact duplicate | I128: Related edition, supporting context or superseded source; no independent trial inferred | J128: No owner production trial log found | K128: English (text screening) | L128: No explicit version established; modified date is file metadata only | M128: extracted pages/blocks/rows; recipe keyword signals (not recipe count)
A129: S033 | B129: nkambe_bakery_commercial_blueprint.pdf | C129: C:\Users\J COMPUTER\Downloads\nkambe_bakery_commercial_blueprint.pdf | D129: .pdf | E129: 2026-10-01T14:03:35.507036+00:00 | F129: 4229 | G129: d94a9284d9a0f1b3afff6086a82905254db760e20f86d0121d07c22203679580 | H129: Extracted text | I129: Related edition, supporting context or superseded source; no independent trial inferred | J129: No owner production trial log found | K129: English (text screening) | L129: No explicit version established; modified date is file metadata only | M129: 2 extracted pages/blocks/rows; 0 recipe keyword signals (not recipe count)
A130: S034 | B130: nkambe_bakery_frozen_empire_manual.pdf | C130: C:\Users\J COMPUTER\Downloads\nkambe_bakery_frozen_empire_manual.pdf | D130: .pdf | E130: 2026-10-01T14:46:15.085825+00:00 | F130: 11374 | G130: 92fe126e3dfb5c34536374c1f63818d3c4d4fffe048ac038ddd798584e53a100 | H130: Extracted text | I130: Related edition, supporting context or superseded source; no independent trial inferred | J130: No owner production trial log found | K130: English (text screening) | L130: No explicit version established; modified date is file metadata only | M130: 4 extracted pages/blocks/rows; 22 recipe keyword signals (not recipe count)
A131: S013 | B131: Nkambe_Bakery_Product_Development_and_Profitability_Strategy.pdf | C131: C:\Users\J COMPUTER\Downloads\Nkambe_Bakery_Product_Development_and_Profitability_Strategy.pdf | D131: .pdf | E131: 2026-10-08T12:08:08.212843+00:00 | F131: 118715 | G131: e8f97c198f48cc035c0576d1a468fb627c37ddc51d0f8658281053a950ac8b84 | H131: Exact duplicate | I131: Recipe source or technical context included | J131: No owner production trial log found | K131: English (text screening) | L131: No explicit version established; modified date is file metadata only | M131: extracted pages/blocks/rows; recipe keyword signals (not recipe count)
A132: S035 | B132: Professional Popsicle production.docx | C132: C:\Users\J COMPUTER\Downloads\Professional Popsicle production.docx | D132: .docx | E132: 2026-07-31T11:18:08.333180+00:00 | F132: 18845 | G132: 143f4f3edd4519afcd071ea3fdaf0a79197473131e8145ea1368f172ffa4c41e | H132: Extracted text | I132: Recipe source or technical context included | J132: No owner production trial log found | K132: English (text screening) | L132: No explicit version established; modified date is file metadata only | M132: 41 extracted pages/blocks/rows; 0 recipe keyword signals (not recipe count)
A133: S036 | B133: Recettes_Magnum.pdf | C133: C:\Users\J COMPUTER\Downloads\Recettes_Magnum.pdf | D133: .pdf | E133: 2026-07-31T11:44:23.305031+00:00 | F133: 4170277 | G133: db2bcdafd28323e03f8846f21dd0314d56b1700e0f907f57f5830769f5ccebe3 | H133: Extracted text | I133: Recipe source or technical context included | J133: No owner production trial log found | K133: French (text screening) | L133: No explicit version established; modified date is file metadata only | M133: 20 extracted pages/blocks/rows; 16 recipe keyword signals (not recipe count)
A134: S037 | B134: shawarma_garlic_sauces_recipe.md | C134: C:\Users\J COMPUTER\Downloads\shawarma_garlic_sauces_recipe.md | D134: .md | E134: 2026-10-01T13:51:51.847904+00:00 | F134: 2614 | G134: ddbd99adb74bf8e6bec6448fffcd5ddd48ed90b9dd40045e3a3b806dfd7506a0 | H134: Extracted text | I134: Recipe source or technical context included | J134: No owner production trial log found | K134: English (text screening) | L134: No explicit version established; modified date is file metadata only | M134: 50 extracted pages/blocks/rows; 2 recipe keyword signals (not recipe count)
A135: S038 | B135: Staggered_Baguette_Production_Schedule.pdf | C135: C:\Users\J COMPUTER\Downloads\Staggered_Baguette_Production_Schedule.pdf | D135: .pdf | E135: 2026-09-11T13:45:25.992631+00:00 | F135: 5904 | G135: e91727846771163e63645761815309a1182bf4f601baf39cb95b67c1b79b17dd | H135: Extracted text | I135: H2 primary requested baguette scheduling source; pp1–2 audited, corrected in BAG-H2-01 and PLAN-BAG-P/N/H | J135: No owner production trial log found | K135: English (text screening) | L135: No explicit version established; modified date is file metadata only | M135: 2 extracted pages/blocks/rows; 2 recipe keyword signals (not recipe count)
B136: ~$ofessional Popsicle production.docx | C136: C:\Users\J COMPUTER\Downloads\~$ofessional Popsicle production.docx | D136: .docx | E136: 2026-07-31T11:18:08.336235+00:00 | F136: 162 | H136: Office lock file | I136: Filename screened | J136: No owner production trial log found | K136: Not established / non-text | L136: No explicit version established; modified date is file metadata only | M136: extracted pages/blocks/rows; recipe keyword signals (not recipe count)
A137: S039 | B137: Nkambe_Bakery_Strategy_and_Recipe_Manual.pdf | C137: C:\Users\J COMPUTER\Nkambe_Bakery_Strategy_and_Recipe_Manual.pdf | D137: .pdf | E137: 2026-09-14T13:56:25.772076+00:00 | F137: 427422 | G137: 2de9eee58228ee341e862fce77da7a93d5316c9a24dded67fca5fcf787342a29 | H137: Extracted text | I137: Related edition, supporting context or superseded source; no independent trial inferred | J137: No owner production trial log found | K137: English (text screening) | L137: No explicit version established; modified date is file metadata only | M137: 89 extracted pages/blocks/rows; 463 recipe keyword signals (not recipe count)
A138: S040 | B138: As a seasoned professional yogurt manufacturer.docx | C138: C:\Users\J COMPUTER\OneDrive - Questindustries\As a seasoned professional yogurt manufacturer.docx | D138: .docx | E138: 2024-10-12T18:33:11+00:00 | F138: 22036 | G138: b1e5c74ff5376b6790a989d8df6f22daae9ae0962a8e14361718e580421619fa | H138: Extracted text | I138: Unsafe/incomplete yogurt procedure; superseded by C04, retained in issue record | J138: No owner production trial log found | K138: English (text screening) | L138: No explicit version established; modified date is file metadata only | M138: 79 extracted pages/blocks/rows; 0 recipe keyword signals (not recipe count)
A139: S041 | B139: 16 32 64 trays rotary oven.pdf | C139: C:\Users\J COMPUTER\OneDrive - Questindustries\bakery pdfs\16 32 64 trays rotary oven.pdf | D139: .pdf | E139: 2025-03-30T08:20:26+00:00 | F139: 241712 | G139: e2c03ebe66d665b72d0c8c2bfc6d4c69ffb1764eefb739a823affa22e5808450 | H139: Extracted text | I139: Equipment/purchase context only; not proof of installed specification | J139: No owner production trial log found | K139: Not established / non-text | L139: No explicit version established; modified date is file metadata only | M139: 2 extracted pages/blocks/rows; 0 recipe keyword signals (not recipe count)
A140: S042 | B140: 16+32+64+trays+rotary+oven.pdf | C140: C:\Users\J COMPUTER\OneDrive - Questindustries\bakery pdfs\16+32+64+trays+rotary+oven.pdf | D140: .pdf | E140: 2025-03-30T08:09:54+00:00 | F140: 242252 | G140: dddb4359df2f96f7f548133b256eb493f36e9e1fca51bbe366b3b2eaaa59bff0 | H140: Extracted text | I140: Equipment/purchase context only; not proof of installed specification | J140: No owner production trial log found | K140: Not established / non-text | L140: No explicit version established; modified date is file metadata only | M140: 2 extracted pages/blocks/rows; 0 recipe keyword signals (not recipe count)
A141: I02 | B141: 21b797e8e663f2790871ba24c8393040.png | C141: C:\Users\J COMPUTER\OneDrive - Questindustries\bakery pdfs\21b797e8e663f2790871ba24c8393040.png | D141: .png | E141: 2025-04-01T08:58:16+00:00 | F141: 279592 | H141: Visually screened relevant images; original preserved | I141: Image screening: burger reference, workbook screenshot or equipment photo; unrelated exam images excluded | J141: No owner production trial log found | K141: Not established / non-text | L141: No explicit version established; modified date is file metadata only | M141: extracted pages/blocks/rows; recipe keyword signals (not recipe count)
A142: I03 | B142: 3ae06b491aa9f9a58355d664ac2aa69b (1).jpg | C142: C:\Users\J COMPUTER\OneDrive - Questindustries\bakery pdfs\3ae06b491aa9f9a58355d664ac2aa69b (1).jpg | D142: .jpg | E142: 2025-03-17T17:24:59+00:00 | F142: 1052574 | H142: Visually screened relevant images; original preserved | I142: Image screening: burger reference, workbook screenshot or equipment photo; unrelated exam images excluded | J142: No owner production trial log found | K142: Not established / non-text | L142: No explicit version established; modified date is file metadata only | M142: extracted pages/blocks/rows; recipe keyword signals (not recipe count)
A143: S043 | B143: Alice wang PI for pullman baking pans and trays 2025.pdf | C143: C:\Users\J COMPUTER\OneDrive - Questindustries\bakery pdfs\Alice wang PI for pullman baking pans and trays 2025.pdf | D143: .pdf | E143: 2025-03-14T06:06:11+00:00 | F143: 139202 | G143: 8b5ed97f2e732fe285be3f581d186852488351613766d8cfc0f3df31280931d2 | H143: Extracted text | I143: Equipment/purchase context only; not proof of installed specification | J143: No owner production trial log found | K143: Not established / non-text | L143: No explicit version established; modified date is file metadata only | M143: 1 extracted pages/blocks/rows; 0 recipe keyword signals (not recipe count)
A144: S044 | B144: Bakery recipes incllud galette 14th Jan 2025_001-KOUATCHOUA.xlsx | C144: C:\Users\J COMPUTER\OneDrive - Questindustries\bakery pdfs\Bakery recipes incllud galette 14th Jan 2025_001-KOUATCHOUA.xlsx | D144: .xlsx | E144: 2025-09-08T07:07:22+00:00 | F144: 82910 | G144: 8a3382fdd72093630ecd88fc9e27e714919bc8c357c90bfbd3af85d8696f3c69 | H144: Extracted text | I144: Recipe source or technical context included | J144: No owner production trial log found | K144: English (text screening) | L144: No explicit version established; modified date is file metadata only | M144: 510 extracted pages/blocks/rows; 32 recipe keyword signals (not recipe count)
A145: S045 | B145: Bakery recipes incllud galette 14th Jan 2025_001.xlsx | C145: C:\Users\J COMPUTER\OneDrive - Questindustries\bakery pdfs\Bakery recipes incllud galette 14th Jan 2025_001.xlsx | D145: .xlsx | E145: 2025-09-28T09:59:33+00:00 | F145: 82694 | G145: d9fb10325e1ed9f3ee17a465f62a456f9f229b52ecf5a067020c0a2430882f15 | H145: Extracted text | I145: Recipe source or technical context included | J145: No owner production trial log found | K145: English (text screening) | L145: No explicit version established; modified date is file metadata only | M145: 508 extracted pages/blocks/rows; 32 recipe keyword signals (not recipe count)
A146: S046 | B146: Bakery recipes Jan 2025 2.xlsx | C146: C:\Users\J COMPUTER\OneDrive - Questindustries\bakery pdfs\Bakery recipes Jan 2025 2.xlsx | D146: .xlsx | E146: 2026-01-07T15:32:22.089029+00:00 | F146: 100429 | G146: e7894287e09f5c53a62704999c2f14d1d0d35ef76f7269d127f4422ff44ba205 | H146: Extracted text | I146: Recipe source or technical context included | J146: No owner production trial log found | K146: English (text screening) | L146: No explicit version established; modified date is file metadata only | M146: 591 extracted pages/blocks/rows; 36 recipe keyword signals (not recipe count)
A147: S047 | B147: Bakery recipes Jan 2025.xlsx | C147: C:\Users\J COMPUTER\OneDrive - Questindustries\bakery pdfs\Bakery recipes Jan 2025.xlsx | D147: .xlsx | E147: 2025-09-08T06:34:28+00:00 | F147: 100219 | G147: 63f55b2e66068d8a7c27384e332f879238f09288ed94e225ba42cfd72f896047 | H147: Extracted text | I147: Recipe source or technical context included | J147: No owner production trial log found | K147: English (text screening) | L147: No explicit version established; modified date is file metadata only | M147: 591 extracted pages/blocks/rows; 36 recipe keyword signals (not recipe count)
A148: S048 | B148: Bakery recipes Jan 20252.xlsx | C148: C:\Users\J COMPUTER\OneDrive - Questindustries\bakery pdfs\Bakery recipes Jan 20252.xlsx | D148: .xlsx | E148: 2025-04-07T07:55:11+00:00 | F148: 108582 | G148: 3916bb5987cb201f20ba2e8dfd3d8dcd98f4afb5221e4e8c99cab9be988f1f0d | H148: Extracted text | I148: Recipe source or technical context included | J148: No owner production trial log found | K148: English (text screening) | L148: No explicit version established; modified date is file metadata only | M148: 627 extracted pages/blocks/rows; 39 recipe keyword signals (not recipe count)
A149: S049 | B149: BREAD-BAKING-UNIVERSITY-SERIES-BUNDLEBread-Recipes-Flour-Production-Bakery-Operations-.pdf | C149: C:\Users\J COMPUTER\OneDrive - Questindustries\bakery pdfs\BREAD-BAKING-UNIVERSITY-SERIES-BUNDLEBread-Recipes-Flour-Production-Bakery-Operations-.pdf | D149: .pdf | E149: 2025-05-11T10:24:51+00:00 | F149: 1341554 | G149: cec871f3b10c8ad696b671533c1b39c01d011d112c3b0f44844296e8efc8111d | H149: Extracted text | I149: Recipe source or technical context included | J149: No owner production trial log found | K149: English (text screening) | L149: No explicit version established; modified date is file metadata only | M149: 67 extracted pages/blocks/rows; 119 recipe keyword signals (not recipe count)
A150: S050 | B150: bread_fillings_recipe_sheet.pdf | C150: C:\Users\J COMPUTER\OneDrive - Questindustries\bakery pdfs\bread_fillings_recipe_sheet.pdf | D150: .pdf | E150: 2025-09-02T08:03:41+00:00 | F150: 373063 | G150: 427b23686fa954f776641a13d1e2aa88d401b19aaab60404a79c573a51c6f7f1 | H150: Locally OCR recovered; adopted quantities require image check | I150: Recipe source or technical context included | J150: No owner production trial log found | K150: Not established / non-text | L150: No explicit version established; modified date is file metadata only | M150: 5 extracted pages/blocks/rows; 0 recipe keyword signals (not recipe count)
A151: S051 | B151: chrome-extension___mhjfbmdgcfjbbpaeojofohoefgiehjai_edge_pdf_index.pdf | C151: C:\Users\J COMPUTER\OneDrive - Questindustries\bakery pdfs\chrome-extension___mhjfbmdgcfjbbpaeojofohoefgiehjai_edge_pdf_index.pdf | D151: .pdf | E151: 2025-03-14T05:10:08+00:00 | F151: 139125 | G151: 7d3dc33199e198a360b10145716452f2e60dc63ef0f5ec0268af40ca9542d981 | H151: Extracted text | I151: Equipment/purchase context only; not proof of installed specification | J151: No owner production trial log found | K151: Not established / non-text | L151: No explicit version established; modified date is file metadata only | M151: 1 extracted pages/blocks/rows; 0 recipe keyword signals (not recipe count)
A152: I04 | B152: d4934413c32ffd1f3f4b5e696b374614.jpg | C152: C:\Users\J COMPUTER\OneDrive - Questindustries\bakery pdfs\d4934413c32ffd1f3f4b5e696b374614.jpg | D152: .jpg | E152: 2025-03-17T17:24:54+00:00 | F152: 2578357 | H152: Visually screened relevant images; original preserved | I152: Image screening: burger reference, workbook screenshot or equipment photo; unrelated exam images excluded | J152: No owner production trial log found | K152: Not established / non-text | L152: No explicit version established; modified date is file metadata only | M152: extracted pages/blocks/rows; recipe keyword signals (not recipe count)
A153: S052 | B153: Diesel rotary oven to kouatchoua mark 202250612.pdf | C153: C:\Users\J COMPUTER\OneDrive - Questindustries\bakery pdfs\Diesel rotary oven to kouatchoua mark 202250612.pdf | D153: .pdf | E153: 2025-07-24T07:18:12+00:00 | F153: 375889 | G153: 7e2ea328017f3be2b93782c19367777e1ad6eda79e5398ef8e9db59d5fda7d40 | H153: Extracted text | I153: Equipment/purchase context only; not proof of installed specification | J153: No owner production trial log found | K153: English (text screening) | L153: No explicit version established; modified date is file metadata only | M153: 2 extracted pages/blocks/rows; 0 recipe keyword signals (not recipe count)
A154: I05 | B154: diesel rotary ovens from Rachel Wang.jpg | C154: C:\Users\J COMPUTER\OneDrive - Questindustries\bakery pdfs\diesel rotary ovens from Rachel Wang.jpg | D154: .jpg | E154: 2025-07-24T07:09:30+00:00 | F154: 758998 | H154: Visually screened relevant images; original preserved | I154: Image screening: burger reference, workbook screenshot or equipment photo; unrelated exam images excluded | J154: No owner production trial log found | K154: Not established / non-text | L154: No explicit version established; modified date is file metadata only | M154: extracted pages/blocks/rows; recipe keyword signals (not recipe count)
A155: S053 | B155: document-1733898008081.pdf | C155: C:\Users\J COMPUTER\OneDrive - Questindustries\bakery pdfs\document-1733898008081.pdf | D155: .pdf | E155: 2025-03-22T09:45:18+00:00 | F155: 86632 | G155: bd675f1e1b953f4cf83ef4d0b5df39f30b593309a9610c714d82f6bc3930d04a | H155: Extracted text | I155: Equipment/purchase context only; not proof of installed specification | J155: No owner production trial log found | K155: Not established / non-text | L155: No explicit version established; modified date is file metadata only | M155: 1 extracted pages/blocks/rows; 0 recipe keyword signals (not recipe count)
A156: S054 | B156: dough sheeter quotation（起酥机）.pdf | C156: C:\Users\J COMPUTER\OneDrive - Questindustries\bakery pdfs\dough sheeter quotation（起酥机）.pdf | D156: .pdf | E156: 2025-04-01T08:05:06+00:00 | F156: 361510 | G156: 8d4dcf13bb29f8d9a353931b8a03910610d034b557b63de789d16908023fe310 | H156: Extracted text | I156: Equipment/purchase context only; not proof of installed specification | J156: No owner production trial log found | K156: English (text screening) | L156: No explicit version established; modified date is file metadata only | M156: 3 extracted pages/blocks/rows; 0 recipe keyword signals (not recipe count)
A157: S055 | B157: Exported Users Sat Mar 15 2025.xlsx | C157: C:\Users\J COMPUTER\OneDrive - Questindustries\bakery pdfs\Exported Users Sat Mar 15 2025.xlsx | D157: .xlsx | E157: 2025-03-15T13:46:54+00:00 | F157: 19296 | G157: 819761a6a2ab7101e4e49a2058145beb6013731c3c77b36bb280b7c5b48d4bac | H157: Excluded: unrelated administrative, software or purchasing material | I157: Not a food recipe | J157: No owner production trial log found | K157: Not established / non-text | L157: No explicit version established; modified date is file metadata only | M157: 6 extracted pages/blocks/rows; 0 recipe keyword signals (not recipe count)
A158: I06 | B158: fb69b1a3312060c57a854dd4f8a25b65.jpg | C158: C:\Users\J COMPUTER\OneDrive - Questindustries\bakery pdfs\fb69b1a3312060c57a854dd4f8a25b65.jpg | D158: .jpg | E158: 2025-03-17T17:25:03+00:00 | F158: 2791521 | H158: Visually screened relevant images; original preserved | I158: Image screening: burger reference, workbook screenshot or equipment photo; unrelated exam images excluded | J158: No owner production trial log found | K158: Not established / non-text | L158: No explicit version established; modified date is file metadata only | M158: extracted pages/blocks/rows; recipe keyword signals (not recipe count)
A159: S056 | B159: hamburger Mc Donalds.pdf | C159: C:\Users\J COMPUTER\OneDrive - Questindustries\bakery pdfs\hamburger Mc Donalds.pdf | D159: .pdf | E159: 2025-07-27T12:45:16+00:00 | F159: 140177 | G159: ceba0ca64fe1e164057e80b9c088289202cb1339a895abc94a9b90fe4a7ec88e | H159: Locally OCR recovered; adopted quantities require image check | I159: Recipe source or technical context included | J159: No owner production trial log found | K159: Not established / non-text | L159: No explicit version established; modified date is file metadata only | M159: 2 extracted pages/blocks/rows; 0 recipe keyword signals (not recipe count)
A160: S057 | B160: Hanbeter Proforma Invoice 20250314H01.pdf | C160: C:\Users\J COMPUTER\OneDrive - Questindustries\bakery pdfs\Hanbeter Proforma Invoice 20250314H01.pdf | D160: .pdf | E160: 2025-03-17T08:53:12+00:00 | F160: 255026 | G160: 327b68ae13b485eab062b74f5f1c934267981037550cea1016653c4bf75228aa | H160: Extracted text | I160: Equipment/purchase context only; not proof of installed specification | J160: No owner production trial log found | K160: English (text screening) | L160: No explicit version established; modified date is file metadata only | M160: 2 extracted pages/blocks/rows; 0 recipe keyword signals (not recipe count)
A161: S058 | B161: Hanbeter Proforma Invoice 20250314H012.pdf | C161: C:\Users\J COMPUTER\OneDrive - Questindustries\bakery pdfs\Hanbeter Proforma Invoice 20250314H012.pdf | D161: .pdf | E161: 2025-03-14T20:08:06+00:00 | F161: 255117 | G161: c549bd8da6dba9b02ab4108dbbcc8cec8752164aa5d118834575386ad72491c6 | H161: Extracted text | I161: Equipment/purchase context only; not proof of installed specification | J161: No owner production trial log found | K161: English (text screening) | L161: No explicit version established; modified date is file metadata only | M161: 2 extracted pages/blocks/rows; 0 recipe keyword signals (not recipe count)
...

Sheet EDC correction
A1: H3 supersedes the EDC interpretation in H1/H2
A2: EDC is not butter and must not be treated or priced as margarine. Its identity, specification, permitted application, dose and purchase price remain unresolved. Keep EDC as a separate historical ingredient and hold affected formulas until it is identified. The earlier owner-workbook butter-to-margarine instruction remains separate; true dairy butter in independent recipes retains its specification. Milk tantalizer and improver remain omitted from revised recipes.
A3: EDC identity remains unresolved. H05 and T01 are held. No EDC price or production dose is inferred.
A4: L004 | B4: Beignet soufle | C4: S132 | D4: 'Beignet soufle'!C14,D14 | E4: 25 | F4: 2.5 | G4: 763.27778 | H4: HOLD; identity and price unresolved
A5: L005 | B5: Beignet soufle | C5: S132 | D5: 'Beignet soufle'!C14,H14 | E5: 83.333333 | F5: 1.6666667 | G5: 717.05556 | H5: HOLD; identity and price unresolved
A6: L015 | B6: Danisa biscuits | C6: S132 | D6: 'Danisa biscuits'!C12,D12 | E6: 50 | F6: 2.7777778 | G6: 1425.5247 | H6: HOLD; identity and price unresolved
A7: L016 | B7: Delice | C7: S132 | D7: 'Delice'!C17,D17 | E7: 50 | F7: 16.666667 | G7: 725.15741 | H7: HOLD; identity and price unresolved
A8: L017 | B8: Delice | C8: S132 | D8: 'Delice'!C17,H17 | E8: 100 | F8: 50 | G8: 1468.3333 | H8: HOLD; identity and price unresolved
A9: L021 | B9: Galette | C9: S132 | D9: 'Galette'!C16,D16 | E9: 75 | F9: 7.5 | G9: 632.80556 | H9: HOLD; identity and price unresolved
A10: L022 | B10: Galette | C10: S132 | D10: 'Galette'!C16,H16 | E10: 100 | F10: 20 | G10: 635.94444 | H10: HOLD; identity and price unresolved
A11: L023 | B11: Hamburger buns | C11: S132 | D11: 'Hamburger buns'!C12,D12 | E11: 20 | F11: 2 | G11: 491.93889 | H11: HOLD; identity and price unresolved
A12: L024 | B12: Hamburger buns | C12: S132 | D12: 'Hamburger buns'!C12,F12 | E12: 333.3333 | F12: 6.6666667 | G12: 511.57407 | H12: HOLD; identity and price unresolved
A13: L034 | B13: NEW BRIOCHE | C13: S132 | D13: 'NEW BRIOCHE'!C15,D15 | E13: 25 | F13: 2.5 | G13: 875 | H13: HOLD; identity and price unresolved
A14: L039 | B14: Pain au lait | C14: S132 | D14: 'Pain au lait'!C16,D16 | E14: 25 | F14: 2.0833333 | G14: 637.59229 | H14: HOLD; identity and price unresolved
A15: L040 | B15: Pain au lait | C15: S132 | D15: 'Pain au lait'!C16,L16 | E15: 12.5 | F15: 1.7857143 | G15: 632.71601 | H15: HOLD; identity and price unresolved
... A95: L251 | B95: YUMMY BREAD | C95: S143 | D95: 'YUMMY BREAD'!C16,D16 | E95: 50 | F95: 4.1666667 | G95: 726.15942 | H95: HOLD; identity and price unresolved
